{"version": 0.6, "generator": "Overpass API 0.7.59.4 36d058c8", "osm3s": {"timestamp_osm_base": "2023-03-22T19:43:56Z", "copyright": "The data included in this document is from www.openstreetmap.org. The data is made available under ODbL."}, "elements": [{"type": "node", "id": 197402969, "lat": 39.2261764, "lon": -84.5491336}, {"type": "node", "id": 197402971, "lat": 39.2261839, "lon": -84.548704, "tags": {"highway": "traffic_signals"}}, {"type": "node", "id": 197407522, "lat": 39.2352462, "lon": -84.558176}, {"type": "node", "id": 197407524, "lat": 39.235603, "lon": -84.558077}, {"type": "node", "id": 197409121, "lat": 39.227116, "lon": -84.556125}, {"type": "node", "id": 197409123, "lat": 39.2272357, "lon": -84.5579038}, {"type": "node", "id": 197416132, "lat": 39.228796, "lon": -84.547195}, {"type": "node", "id": 197416135, "lat": 39.231428, "lon": -84.546981}, {"type": "node", "id": 197416139, "lat": 39.233455, "lon": -84.546789}, {"type": "node", "id": 197416141, "lat": 39.234436, "lon": -84.546706}, {"type": "node", "id": 197416146, "lat": 39.235958, "lon": -84.546579}, {"type": "node", "id": 197418748, "lat": 39.234499, "lon": -84.548026}, {"type": "node", "id": 197418749, "lat": 39.234566, "lon": -84.549327}, {"type": "node", "id": 197418751, "lat": 39.234629, "lon": -84.550586}, {"type": "node", "id": 197422286, "lat": 39.225417, "lon": -84.55543}, {"type": "node", "id": 197423688, "lat": 39.224668, "lon": -84.555301}, {"type": "node", "id": 197426464, "lat": 39.233974, "lon": -84.570006}, {"type": "node", "id": 197426517, "lat": 39.242883, "lon": -84.568524}, {"type": "node", "id": 197429964, "lat": 39.228443, "lon": -84.543693}, {"type": "node", "id": 197429969, "lat": 39.2330474, "lon": -84.5432819}, {"type": "node", "id": 197436127, "lat": 39.2299453, "lon": -84.5570413}, {"type": "node", "id": 197436128, "lat": 39.230561, "lon": -84.556982}, {"type": "node", "id": 197436129, "lat": 39.231809, "lon": -84.556868}, {"type": "node", "id": 197442691, "lat": 39.229297, "lon": -84.554588}, {"type": "node", "id": 197442692, "lat": 39.228169, "lon": -84.554678}, {"type": "node", "id": 197448736, "lat": 39.23697, "lon": -84.547811, "tags": {"highway": "traffic_signals"}}, {"type": "node", "id": 197448738, "lat": 39.237055, "lon": -84.549121}, {"type": "node", "id": 197448742, "lat": 39.237413, "lon": -84.55499}, {"type": "node", "id": 197448744, "lat": 39.237614, "lon": -84.557824}, {"type": "node", "id": 197448746, "lat": 39.237628, "lon": -84.558025}, {"type": "node", "id": 197448748, "lat": 39.237685, "lon": -84.558837}, {"type": "node", "id": 197448782, "lat": 39.237898, "lon": -84.558928}, {"type": "node", "id": 197448783, "lat": 39.239093, "lon": -84.55939}, {"type": "node", "id": 197448784, "lat": 39.239314, "lon": -84.559459}, {"type": "node", "id": 197448785, "lat": 39.239484, "lon": -84.559492}, {"type": "node", "id": 197448787, "lat": 39.239771, "lon": -84.559518}, {"type": "node", "id": 197448788, "lat": 39.2399133, "lon": -84.5595486}, {"type": "node", "id": 197448789, "lat": 39.240023, "lon": -84.559598}, {"type": "node", "id": 197448791, "lat": 39.240219, "lon": -84.559706}, {"type": "node", "id": 197448792, "lat": 39.240464, "lon": -84.559852}, {"type": "node", "id": 197448794, "lat": 39.240554, "lon": -84.559901}, {"type": "node", "id": 197448796, "lat": 39.240855, "lon": -84.560092}, {"type": "node", "id": 197448798, "lat": 39.24145, "lon": -84.560496}, {"type": "node", "id": 197448800, "lat": 39.241703, "lon": -84.560668}, {"type": "node", "id": 197448802, "lat": 39.242053, "lon": -84.560917}, {"type": "node", "id": 197448804, "lat": 39.242214, "lon": -84.561053}, {"type": "node", "id": 197448806, "lat": 39.242366, "lon": -84.561207}, {"type": "node", "id": 197448808, "lat": 39.242477, "lon": -84.56134}, {"type": "node", "id": 197448810, "lat": 39.242587, "lon": -84.561496}, {"type": "node", "id": 197448812, "lat": 39.2426737, "lon": -84.5616717}, {"type": "node", "id": 197448815, "lat": 39.242822, "lon": -84.561911}, {"type": "node", "id": 197448817, "lat": 39.242911, "lon": -84.5621}, {"type": "node", "id": 197448819, "lat": 39.243018, "lon": -84.562364}, {"type": "node", "id": 197448821, "lat": 39.243056, "lon": -84.562483}, {"type": "node", "id": 197448823, "lat": 39.243152, "lon": -84.562874}, {"type": "node", "id": 197448825, "lat": 39.243178, "lon": -84.563015}, {"type": "node", "id": 197448827, "lat": 39.24321, "lon": -84.563303}, {"type": "node", "id": 197448829, "lat": 39.243229, "lon": -84.563594}, {"type": "node", "id": 197448831, "lat": 39.2433, "lon": -84.564897}, {"type": "node", "id": 197448833, "lat": 39.243379, "lon": -84.566417}, {"type": "node", "id": 197448835, "lat": 39.243372, "lon": -84.566493}, {"type": "node", "id": 197448837, "lat": 39.243362, "lon": -84.566599}, {"type": "node", "id": 197448839, "lat": 39.243325, "lon": -84.566813}, {"type": "node", "id": 197448841, "lat": 39.243274, "lon": -84.567018}, {"type": "node", "id": 197448842, "lat": 39.243198, "lon": -84.567246}, {"type": "node", "id": 197448843, "lat": 39.243138, "lon": -84.5674}, {"type": "node", "id": 197448845, "lat": 39.242994, "lon": -84.567799}, {"type": "node", "id": 197448848, "lat": 39.242947, "lon": -84.56796}, {"type": "node", "id": 197448850, "lat": 39.242907, "lon": -84.568168}, {"type": "node", "id": 197448852, "lat": 39.242886, "lon": -84.568382}, {"type": "node", "id": 197448853, "lat": 39.242906, "lon": -84.569002}, {"type": "node", "id": 197448856, "lat": 39.242957, "lon": -84.570468}, {"type": "node", "id": 197448858, "lat": 39.243021, "lon": -84.572097}, {"type": "node", "id": 197448860, "lat": 39.243047, "lon": -84.572875}, {"type": "node", "id": 197448862, "lat": 39.243117, "lon": -84.574583}, {"type": "node", "id": 197448865, "lat": 39.243126, "lon": -84.574936}, {"type": "node", "id": 197452746, "lat": 39.231812, "lon": -84.553041}, {"type": "node", "id": 197452748, "lat": 39.231852, "lon": -84.55303}, {"type": "node", "id": 197452750, "lat": 39.232273, "lon": -84.55299}, {"type": "node", "id": 197452781, "lat": 39.231497, "lon": -84.548273, "tags": {"highway": "traffic_signals"}}, {"type": "node", "id": 197452783, "lat": 39.231567, "lon": -84.549584}, {"type": "node", "id": 197452786, "lat": 39.231655, "lon": -84.550829}, {"type": "node", "id": 197452788, "lat": 39.231727, "lon": -84.552027}, {"type": "node", "id": 197452790, "lat": 39.231742, "lon": -84.552088}, {"type": "node", "id": 197464796, "lat": 39.243961, "lon": -84.547192, "tags": {"highway": "traffic_signals"}}, {"type": "node", "id": 197473032, "lat": 39.223185, "lon": -84.555441}, {"type": "node", "id": 197479101, "lat": 39.230074, "lon": -84.548388}, {"type": "node", "id": 197479103, "lat": 39.230149, "lon": -84.549704}, {"type": "node", "id": 197479105, "lat": 39.230219, "lon": -84.550947}, {"type": "node", "id": 197479106, "lat": 39.230287, "lon": -84.552163}, {"type": "node", "id": 197479108, "lat": 39.230346, "lon": -84.553166}, {"type": "node", "id": 197479110, "lat": 39.230439, "lon": -84.554787}, {"type": "node", "id": 197479112, "lat": 39.230494, "lon": -84.555822}, {"type": "node", "id": 197479114, "lat": 39.230633, "lon": -84.558183}, {"type": "node", "id": 197485936, "lat": 39.22857, "lon": -84.544973}, {"type": "node", "id": 197485952, "lat": 39.233144, "lon": -84.544466}, {"type": "node", "id": 197497815, "lat": 39.2332, "lon": -84.544944}, {"type": "node", "id": 197497817, "lat": 39.233232, "lon": -84.545157}, {"type": "node", "id": 197497819, "lat": 39.233423, "lon": -84.546158}, {"type": "node", "id": 197497821, "lat": 39.233444, "lon": -84.54634}, {"type": "node", "id": 197497825, "lat": 39.233461, "lon": -84.5466869, "tags": {"crossing": "zebra", "highway": "crossing"}}, {"type": "node", "id": 197497827, "lat": 39.233531, "lon": -84.548104, "tags": {"highway": "traffic_signals"}}, {"type": "node", "id": 197497829, "lat": 39.233594, "lon": -84.549408}, {"type": "node", "id": 197505104, "lat": 39.228205, "lon": -84.548564}, {"type": "node", "id": 197505106, "lat": 39.228944, "lon": -84.548504, "tags": {"highway": "traffic_signals"}}, {"type": "node", "id": 197505109, "lat": 39.232512, "lon": -84.548191, "tags": {"highway": "traffic_signals"}}, {"type": "node", "id": 197505110, "lat": 39.2356931, "lon": -84.5479155}, {"type": "node", "id": 197505113, "lat": 39.236021, "lon": -84.547892}, {"type": "node", "id": 197505116, "lat": 39.2367324, "lon": -84.54783}, {"type": "node", "id": 197505118, "lat": 39.238076, "lon": -84.547706}, {"type": "node", "id": 197505121, "lat": 39.2420093, "lon": -84.5473482}, {"type": "node", "id": 197505123, "lat": 39.2421669, "lon": -84.5473343}, {"type": "node", "id": 197505126, "lat": 39.2425719, "lon": -84.5472966}, {"type": "node", "id": 197505130, "lat": 39.242815, "lon": -84.5472763}, {"type": "node", "id": 197505135, "lat": 39.244762, "lon": -84.547135}, {"type": "node", "id": 197505136, "lat": 39.245195, "lon": -84.547096}, {"type": "node", "id": 197506366, "lat": 39.23345, "lon": -84.562733}, {"type": "node", "id": 197506367, "lat": 39.234483, "lon": -84.562653}, {"type": "node", "id": 197506368, "lat": 39.23519, "lon": -84.562604}, {"type": "node", "id": 197506370, "lat": 39.235442, "lon": -84.562587}, {"type": "node", "id": 197506371, "lat": 39.23572, "lon": -84.562546}, {"type": "node", "id": 197506372, "lat": 39.236133, "lon": -84.562463}, {"type": "node", "id": 197506374, "lat": 39.236437, "lon": -84.562423}, {"type": "node", "id": 197506376, "lat": 39.238524, "lon": -84.562267}, {"type": "node", "id": 197506378, "lat": 39.238802, "lon": -84.562254}, {"type": "node", "id": 197506380, "lat": 39.239015, "lon": -84.562227}, {"type": "node", "id": 197506382, "lat": 39.23915, "lon": -84.562192}, {"type": "node", "id": 197506384, "lat": 39.239282, "lon": -84.562139}, {"type": "node", "id": 197506386, "lat": 39.239411, "lon": -84.562074}, {"type": "node", "id": 197506388, "lat": 39.239533, "lon": -84.561988}, {"type": "node", "id": 197506390, "lat": 39.239645, "lon": -84.561882}, {"type": "node", "id": 197506392, "lat": 39.23973, "lon": -84.56178}, {"type": "node", "id": 197506394, "lat": 39.239806, "lon": -84.561666}, {"type": "node", "id": 197506396, "lat": 39.239856, "lon": -84.561574}, {"type": "node", "id": 197506398, "lat": 39.239926, "lon": -84.561421}, {"type": "node", "id": 197510434, "lat": 39.232847, "lon": -84.553419}, {"type": "node", "id": 197510442, "lat": 39.231822, "lon": -84.553439}, {"type": "node", "id": 197514615, "lat": 39.233244, "lon": -84.559547}, {"type": "node", "id": 197514618, "lat": 39.233622, "lon": -84.55951}, {"type": "node", "id": 197514621, "lat": 39.233835, "lon": -84.559489}, {"type": "node", "id": 197514623, "lat": 39.234028, "lon": -84.559416}, {"type": "node", "id": 197514626, "lat": 39.23411, "lon": -84.559369}, {"type": "node", "id": 197514628, "lat": 39.2343699, "lon": -84.5592323}, {"type": "node", "id": 197514631, "lat": 39.234447, "lon": -84.55899}, {"type": "node", "id": 197514633, "lat": 39.234246, "lon": -84.558461}, {"type": "node", "id": 197514635, "lat": 39.234205, "lon": -84.557889}, {"type": "node", "id": 197514638, "lat": 39.234238, "lon": -84.557848}, {"type": "node", "id": 197514640, "lat": 39.235235, "lon": -84.557775}, {"type": "node", "id": 197514642, "lat": 39.235285, "lon": -84.559201}, {"type": "node", "id": 197514643, "lat": 39.234961, "lon": -84.559245}, {"type": "node", "id": 197514645, "lat": 39.234602, "lon": -84.559235}, {"type": "node", "id": 197520887, "lat": 39.228666, "lon": -84.545926}, {"type": "node", "id": 197522548, "lat": 39.2336242, "lon": -84.565427, "tags": {"highway": "traffic_signals"}}, {"type": "node", "id": 197524191, "lat": 39.235215, "lon": -84.550526}, {"type": "node", "id": 197524194, "lat": 39.236007, "lon": -84.550468}, {"type": "node", "id": 197524196, "lat": 39.236057, "lon": -84.550452}, {"type": "node", "id": 197524198, "lat": 39.236104, "lon": -84.550422}, {"type": "node", "id": 197527078, "lat": 39.232764, "lon": -84.552096}, {"type": "node", "id": 197527085, "lat": 39.228142, "lon": -84.552362}, {"type": "node", "id": 197527086, "lat": 39.228326, "lon": -84.552348}, {"type": "node", "id": 197527087, "lat": 39.228415, "lon": -84.552328}, {"type": "node", "id": 197527088, "lat": 39.228567, "lon": -84.552317}, {"type": "node", "id": 197527089, "lat": 39.22902, "lon": -84.552268}, {"type": "node", "id": 197527090, "lat": 39.229165, "lon": -84.55226}, {"type": "node", "id": 197527091, "lat": 39.229329, "lon": -84.552238}, {"type": "node", "id": 197527092, "lat": 39.229407, "lon": -84.552237}, {"type": "node", "id": 197527093, "lat": 39.232755, "lon": -84.551937}, {"type": "node", "id": 197528646, "lat": 39.235103, "lon": -84.560521}, {"type": "node", "id": 197528648, "lat": 39.2350651, "lon": -84.5596866}, {"type": "node", "id": 197543334, "lat": 39.231148, "lon": -84.550871}, {"type": "node", "id": 197543337, "lat": 39.230677, "lon": -84.550922}, {"type": "node", "id": 197543436, "lat": 39.234077, "lon": -84.549369}, {"type": "node", "id": 197543439, "lat": 39.23414, "lon": -84.550526}, {"type": "node", "id": 197557418, "lat": 39.236183, "lon": -84.558034}, {"type": "node", "id": 197557420, "lat": 39.2362243, "lon": -84.5590531, "tags": {"highway": "turning_circle"}}, {"type": "node", "id": 197571782, "lat": 39.2245474, "lon": -84.5743249}, {"type": "node", "id": 197571784, "lat": 39.2244609, "lon": -84.5739215}, {"type": "node", "id": 197571786, "lat": 39.224328, "lon": -84.5733636}, {"type": "node", "id": 197571788, "lat": 39.2241817, "lon": -84.5728658}, {"type": "node", "id": 197571790, "lat": 39.2236763, "lon": -84.5712178}, {"type": "node", "id": 197571792, "lat": 39.2234902, "lon": -84.5706513}, {"type": "node", "id": 197571794, "lat": 39.2233505, "lon": -84.570205}, {"type": "node", "id": 197571796, "lat": 39.2231577, "lon": -84.569484}, {"type": "node", "id": 197571798, "lat": 39.2230114, "lon": -84.5687888}, {"type": "node", "id": 197571807, "lat": 39.2228917, "lon": -84.5681794}, {"type": "node", "id": 197571811, "lat": 39.2227987, "lon": -84.5674928}, {"type": "node", "id": 197571813, "lat": 39.2227322, "lon": -84.5667804}, {"type": "node", "id": 197571815, "lat": 39.2225327, "lon": -84.5637677}, {"type": "node", "id": 197571817, "lat": 39.2225194, "lon": -84.5634759}, {"type": "node", "id": 197571819, "lat": 39.2224994, "lon": -84.5632356}, {"type": "node", "id": 197571821, "lat": 39.2224861, "lon": -84.5629437}, {"type": "node", "id": 197571823, "lat": 39.2224728, "lon": -84.5624803}, {"type": "node", "id": 197571825, "lat": 39.2224861, "lon": -84.5621713}, {"type": "node", "id": 197571827, "lat": 39.2224994, "lon": -84.5619309}, {"type": "node", "id": 197571829, "lat": 39.2225393, "lon": -84.5616305}, {"type": "node", "id": 197571831, "lat": 39.2225992, "lon": -84.5613473}, {"type": "node", "id": 197571833, "lat": 39.2226457, "lon": -84.561167}, {"type": "node", "id": 197571835, "lat": 39.2227122, "lon": -84.5609353}, {"type": "node", "id": 197571837, "lat": 39.2228053, "lon": -84.5606864}, {"type": "node", "id": 197571839, "lat": 39.222925, "lon": -84.5604375}, {"type": "node", "id": 197571841, "lat": 39.223038, "lon": -84.5602229}, {"type": "node", "id": 197571844, "lat": 39.2231511, "lon": -84.5600512}, {"type": "node", "id": 197571847, "lat": 39.2232774, "lon": -84.5598796}, {"type": "node", "id": 197571851, "lat": 39.2234237, "lon": -84.5596908}, {"type": "node", "id": 197571853, "lat": 39.2235766, "lon": -84.5595363}, {"type": "node", "id": 197571855, "lat": 39.2237162, "lon": -84.5593903}, {"type": "node", "id": 197571857, "lat": 39.2238958, "lon": -84.5592273}, {"type": "node", "id": 197571859, "lat": 39.2241019, "lon": -84.5590642}, {"type": "node", "id": 197571861, "lat": 39.2243413, "lon": -84.5588582}, {"type": "node", "id": 197571863, "lat": 39.224574, "lon": -84.558678}, {"type": "node", "id": 197571864, "lat": 39.2248931, "lon": -84.5583861}, {"type": "node", "id": 197571865, "lat": 39.2251325, "lon": -84.5581372}, {"type": "node", "id": 197571869, "lat": 39.2253187, "lon": -84.5579398}, {"type": "node", "id": 197571873, "lat": 39.2254849, "lon": -84.5577167}, {"type": "node", "id": 197571877, "lat": 39.2256378, "lon": -84.5574763}, {"type": "node", "id": 197571879, "lat": 39.2258107, "lon": -84.5571759}, {"type": "node", "id": 197571880, "lat": 39.2259503, "lon": -84.5568583}, {"type": "node", "id": 197571884, "lat": 39.2260567, "lon": -84.5565837}, {"type": "node", "id": 197571886, "lat": 39.2261564, "lon": -84.5562747}, {"type": "node", "id": 197571887, "lat": 39.226203, "lon": -84.5560945}, {"type": "node", "id": 197571893, "lat": 39.2262695, "lon": -84.5557254}, {"type": "node", "id": 197571895, "lat": 39.2262894, "lon": -84.555528}, {"type": "node", "id": 197571897, "lat": 39.226316, "lon": -84.555219}, {"type": "node", "id": 197571898, "lat": 39.2263293, "lon": -84.5549186}, {"type": "node", "id": 197571900, "lat": 39.2263227, "lon": -84.5546182}, {"type": "node", "id": 197571902, "lat": 39.2263027, "lon": -84.5541718}, {"type": "node", "id": 197571904, "lat": 39.2261165, "lon": -84.5517085}, {"type": "node", "id": 197571906, "lat": 39.2260634, "lon": -84.5511163}, {"type": "node", "id": 197571908, "lat": 39.2259969, "lon": -84.5504296}, {"type": "node", "id": 197571914, "lat": 39.2259237, "lon": -84.5497172}, {"type": "node", "id": 197572264, "lat": 39.226516, "lon": -84.556081}, {"type": "node", "id": 197572266, "lat": 39.226626, "lon": -84.556125}, {"type": "node", "id": 197572268, "lat": 39.226739, "lon": -84.556149}, {"type": "node", "id": 197572270, "lat": 39.226826, "lon": -84.556155}, {"type": "node", "id": 197572272, "lat": 39.227886, "lon": -84.556059}, {"type": "node", "id": 197572274, "lat": 39.228904, "lon": -84.555966}, {"type": "node", "id": 197572276, "lat": 39.229382, "lon": -84.555919}, {"type": "node", "id": 197572278, "lat": 39.231742, "lon": -84.555706}, {"type": "node", "id": 197574164, "lat": 39.2343816, "lon": -84.5608754}, {"type": "node", "id": 197574166, "lat": 39.234801, "lon": -84.560611}, {"type": "node", "id": 197574168, "lat": 39.234917, "lon": -84.560564}, {"type": "node", "id": 197574170, "lat": 39.2361, "lon": -84.560459}, {"type": "node", "id": 197574172, "lat": 39.236216, "lon": -84.560474}, {"type": "node", "id": 197574174, "lat": 39.236328, "lon": -84.560511}, {"type": "node", "id": 197574176, "lat": 39.236436, "lon": -84.560568}, {"type": "node", "id": 197574178, "lat": 39.236757, "lon": -84.560757}, {"type": "node", "id": 197574180, "lat": 39.236836, "lon": -84.560789}, {"type": "node", "id": 197574182, "lat": 39.236917, "lon": -84.560809}, {"type": "node", "id": 197574184, "lat": 39.237028, "lon": -84.560815}, {"type": "node", "id": 197574186, "lat": 39.237288, "lon": -84.560793}, {"type": "node", "id": 197574188, "lat": 39.237345, "lon": -84.560772}, {"type": "node", "id": 197574190, "lat": 39.237379, "lon": -84.560749}, {"type": "node", "id": 197574192, "lat": 39.237425, "lon": -84.5607}, {"type": "node", "id": 197574194, "lat": 39.237471, "lon": -84.560624}, {"type": "node", "id": 197574196, "lat": 39.237496, "lon": -84.560561}, {"type": "node", "id": 197574198, "lat": 39.237512, "lon": -84.560494}, {"type": "node", "id": 197574200, "lat": 39.237517, "lon": -84.560424}, {"type": "node", "id": 197574203, "lat": 39.237473, "lon": -84.559767}, {"type": "node", "id": 197574204, "lat": 39.237449, "lon": -84.559222}, {"type": "node", "id": 197574206, "lat": 39.237459, "lon": -84.559144}, {"type": "node", "id": 197574208, "lat": 39.237482, "lon": -84.559071}, {"type": "node", "id": 197574210, "lat": 39.237505, "lon": -84.559028}, {"type": "node", "id": 197574856, "lat": 39.22807, "lon": -84.553357}, {"type": "node", "id": 197574858, "lat": 39.229216, "lon": -84.553258}, {"type": "node", "id": 197574860, "lat": 39.231109, "lon": -84.553106}, {"type": "node", "id": 197574866, "lat": 39.23282, "lon": -84.552995}, {"type": "node", "id": 197584055, "lat": 39.228281, "lon": -84.549867}, {"type": "node", "id": 197596470, "lat": 39.237297, "lon": -84.557845}, {"type": "node", "id": 197596471, "lat": 39.23715, "lon": -84.557876}, {"type": "node", "id": 197596472, "lat": 39.23687, "lon": -84.557967}, {"type": "node", "id": 197596474, "lat": 39.236733, "lon": -84.557993}, {"type": "node", "id": 197601067, "lat": 39.218234, "lon": -84.555905, "tags": {"highway": "traffic_signals", "traffic_signals": "signal"}}, {"type": "node", "id": 197601069, "lat": 39.219406, "lon": -84.555789}, {"type": "node", "id": 197601072, "lat": 39.220869, "lon": -84.555655}, {"type": "node", "id": 197601074, "lat": 39.223924, "lon": -84.555376}, {"type": "node", "id": 197601077, "lat": 39.224809, "lon": -84.555286}, {"type": "node", "id": 197601079, "lat": 39.22495, "lon": -84.555289}, {"type": "node", "id": 197601081, "lat": 39.225091, "lon": -84.555309}, {"type": "node", "id": 197601083, "lat": 39.225229, "lon": -84.555347}, {"type": "node", "id": 197601084, "lat": 39.225364, "lon": -84.555403}, {"type": "node", "id": 197601087, "lat": 39.225574, "lon": -84.555516}, {"type": "node", "id": 197602011, "lat": 39.232596, "lon": -84.549495, "tags": {"highway": "traffic_signals", "traffic_signals": "signal"}}, {"type": "node", "id": 197602013, "lat": 39.232723, "lon": -84.551398}, {"type": "node", "id": 197602015, "lat": 39.233144, "lon": -84.55795, "tags": {"highway": "traffic_signals", "traffic_signals": "signal"}}, {"type": "node", "id": 197602017, "lat": 39.233174, "lon": -84.558441}, {"type": "node", "id": 197602019, "lat": 39.2332657, "lon": -84.5598524}, {"type": "node", "id": 197602021, "lat": 39.233388, "lon": -84.561818}, {"type": "node", "id": 197602023, "lat": 39.233574, "lon": -84.56459}, {"type": "node", "id": 197602025, "lat": 39.233707, "lon": -84.56647}, {"type": "node", "id": 197602027, "lat": 39.233764, "lon": -84.567243}, {"type": "node", "id": 197602029, "lat": 39.233766, "lon": -84.567384}, {"type": "node", "id": 197602031, "lat": 39.233774, "lon": -84.567545}, {"type": "node", "id": 197602033, "lat": 39.2338017, "lon": -84.5680814}, {"type": "node", "id": 197602035, "lat": 39.233942, "lon": -84.569689}, {"type": "node", "id": 197602037, "lat": 39.23411, "lon": -84.571398}, {"type": "node", "id": 197602039, "lat": 39.23414, "lon": -84.571574}, {"type": "node", "id": 197602041, "lat": 39.234181, "lon": -84.571746}, {"type": "node", "id": 197602043, "lat": 39.234247, "lon": -84.571945}, {"type": "node", "id": 197602045, "lat": 39.234313, "lon": -84.572103}, {"type": "node", "id": 197602047, "lat": 39.234408, "lon": -84.572282}, {"type": "node", "id": 197602049, "lat": 39.234498, "lon": -84.57242}, {"type": "node", "id": 197602051, "lat": 39.23464, "lon": -84.572599}, {"type": "node", "id": 197602053, "lat": 39.234705, "lon": -84.572671}, {"type": "node", "id": 197602055, "lat": 39.234898, "lon": -84.572906}, {"type": "node", "id": 197602057, "lat": 39.2350186, "lon": -84.5730837}, {"type": "node", "id": 197602059, "lat": 39.23511, "lon": -84.573237}, {"type": "node", "id": 197602061, "lat": 39.235597, "lon": -84.574182}, {"type": "node", "id": 197602063, "lat": 39.23566, "lon": -84.574332}, {"type": "node", "id": 197602065, "lat": 39.235723, "lon": -84.574532}, {"type": "node", "id": 197602067, "lat": 39.235762, "lon": -84.574707}, {"type": "node", "id": 197602069, "lat": 39.235788, "lon": -84.574886}, {"type": "node", "id": 197602072, "lat": 39.235806, "lon": -84.575141}, {"type": "node", "id": 197612872, "lat": 39.2279575, "lon": -84.5572402, "tags": {"highway": "turning_circle"}}, {"type": "node", "id": 197623999, "lat": 39.229025, "lon": -84.549801}, {"type": "node", "id": 197624001, "lat": 39.229189, "lon": -84.549795}, {"type": "node", "id": 197624003, "lat": 39.231165, "lon": -84.54961}, {"type": "node", "id": 197624004, "lat": 39.236089, "lon": -84.549198}, {"type": "node", "id": 197640117, "lat": 39.2278121, "lon": -84.558423}, {"type": "node", "id": 197640119, "lat": 39.2290529, "lon": -84.5583015}, {"type": "node", "id": 197640121, "lat": 39.229131, "lon": -84.558312}, {"type": "node", "id": 197640123, "lat": 39.23102, "lon": -84.558143}, {"type": "node", "id": 197654929, "lat": 39.2359161, "lon": -84.5458845}, {"type": "node", "id": 197654931, "lat": 39.2359293, "lon": -84.5462445}, {"type": "node", "id": 197654933, "lat": 39.236149, "lon": -84.550312}, {"type": "node", "id": 197654935, "lat": 39.236137, "lon": -84.550364}, {"type": "node", "id": 197654937, "lat": 39.236117, "lon": -84.550406}, {"type": "node", "id": 197678897, "lat": 39.22931, "lon": -84.554754}, {"type": "node", "id": 197678929, "lat": 39.22903, "lon": -84.558047}, {"type": "node", "id": 307930777, "lat": 39.2263834, "lon": -84.5546349}, {"type": "node", "id": 307930778, "lat": 39.2263169, "lon": -84.553047}, {"type": "node", "id": 307930779, "lat": 39.2263094, "lon": -84.5514253}, {"type": "node", "id": 307930780, "lat": 39.2262703, "lon": -84.5505665}, {"type": "node", "id": 307933232, "lat": 39.2258373, "lon": -84.549022}, {"type": "node", "id": 307933255, "lat": 39.2257575, "lon": -84.5484298}, {"type": "node", "id": 307933387, "lat": 39.2246205, "lon": -84.5746768}, {"type": "node", "id": 373771611, "lat": 39.2251657, "lon": -84.5578368}, {"type": "node", "id": 373771614, "lat": 39.2254184, "lon": -84.5575021}, {"type": "node", "id": 373771615, "lat": 39.2256179, "lon": -84.5571588}, {"type": "node", "id": 373771616, "lat": 39.2257974, "lon": -84.5567725}, {"type": "node", "id": 373771617, "lat": 39.2259636, "lon": -84.556309}, {"type": "node", "id": 373771618, "lat": 39.2260501, "lon": -84.55594}, {"type": "node", "id": 373771619, "lat": 39.2261032, "lon": -84.5555881}, {"type": "node", "id": 373771620, "lat": 39.2261343, "lon": -84.5552235}, {"type": "node", "id": 373771621, "lat": 39.2261498, "lon": -84.5548499}, {"type": "node", "id": 373771622, "lat": 39.2261431, "lon": -84.5544894, "tags": {"highway": "motorway_junction", "ref": "22"}}, {"type": "node", "id": 373775206, "lat": 39.2331949, "lon": -84.5587712}, {"type": "node", "id": 373775207, "lat": 39.2335259, "lon": -84.5638704}, {"type": "node", "id": 373775788, "lat": 39.2263426, "lon": -84.5559657}, {"type": "node", "id": 373775827, "lat": 39.2261365, "lon": -84.555837}, {"type": "node", "id": 373775998, "lat": 39.2262429, "lon": -84.5559056}, {"type": "node", "id": 373776639, "lat": 39.2261169, "lon": -84.5554326}, {"type": "node", "id": 373776657, "lat": 39.2259922, "lon": -84.556187}, {"type": "node", "id": 373778458, "lat": 39.2224462, "lon": -84.5651324}, {"type": "node", "id": 373778461, "lat": 39.2223066, "lon": -84.5626347}, {"type": "node", "id": 373778462, "lat": 39.2223199, "lon": -84.5621198}, {"type": "node", "id": 373778463, "lat": 39.2223797, "lon": -84.5615619}, {"type": "node", "id": 373778464, "lat": 39.2224795, "lon": -84.561107}, {"type": "node", "id": 373778467, "lat": 39.2226191, "lon": -84.5606864}, {"type": "node", "id": 373778468, "lat": 39.2227787, "lon": -84.5603173}, {"type": "node", "id": 373778470, "lat": 39.2229915, "lon": -84.5599482}, {"type": "node", "id": 373778471, "lat": 39.2232109, "lon": -84.5596478}, {"type": "node", "id": 373778472, "lat": 39.2234436, "lon": -84.5593818}, {"type": "node", "id": 373778474, "lat": 39.2237162, "lon": -84.5591243}, {"type": "node", "id": 373778475, "lat": 39.2245274, "lon": -84.5584376}, {"type": "node", "id": 373778476, "lat": 39.2248466, "lon": -84.558163}, {"type": "node", "id": 373778570, "lat": 39.2225617, "lon": -84.5642059}, {"type": "node", "id": 373778581, "lat": 39.2223973, "lon": -84.5642572}, {"type": "node", "id": 373779280, "lat": 39.2237295, "lon": -84.5719903}, {"type": "node", "id": 373779281, "lat": 39.223038, "lon": -84.5697072}, {"type": "node", "id": 373779282, "lat": 39.2228053, "lon": -84.5686686}, {"type": "node", "id": 373779283, "lat": 39.2226856, "lon": -84.5679563}, {"type": "node", "id": 373779284, "lat": 39.2226058, "lon": -84.5672696}, {"type": "node", "id": 373779285, "lat": 39.2225393, "lon": -84.5665486}, {"type": "node", "id": 373779915, "lat": 39.2244077, "lon": -84.5744966}, {"type": "node", "id": 373779916, "lat": 39.2243147, "lon": -84.5740588}, {"type": "node", "id": 373779919, "lat": 39.2241883, "lon": -84.5735438}, {"type": "node", "id": 373779920, "lat": 39.2240487, "lon": -84.5730117}, {"type": "node", "id": 373779921, "lat": 39.2239091, "lon": -84.5725482}, {"type": "node", "id": 373779995, "lat": 39.2244574, "lon": -84.5747894}, {"type": "node", "id": 373781729, "lat": 39.2244077, "lon": -84.5736983}, {"type": "node", "id": 373781740, "lat": 39.2242455, "lon": -84.5737767}, {"type": "node", "id": 1070467934, "lat": 39.2325529, "lon": -84.5488259}, {"type": "node", "id": 1070467951, "lat": 39.2345316, "lon": -84.5486592}, {"type": "node", "id": 1070468016, "lat": 39.2317744, "lon": -84.5525285}, {"type": "node", "id": 1070468085, "lat": 39.229247, "lon": -84.5537668}, {"type": "node", "id": 1070468104, "lat": 39.2314615, "lon": -84.5476077}, {"type": "node", "id": 1070468157, "lat": 39.2344071, "lon": -84.546037}, {"type": "node", "id": 1070468212, "lat": 39.2298787, "lon": -84.553204}, {"type": "node", "id": 1070468219, "lat": 39.2334915, "lon": -84.5474201}, {"type": "node", "id": 1070468294, "lat": 39.2305937, "lon": -84.5496629}, {"type": "node", "id": 1070468352, "lat": 39.2344844, "lon": -84.5534151}, {"type": "node", "id": 1070468366, "lat": 39.2303161, "lon": -84.5526706}, {"type": "node", "id": 1070468415, "lat": 39.2359883, "lon": -84.5472113}, {"type": "node", "id": 1070468438, "lat": 39.2330926, "lon": -84.5438702}, {"type": "node", "id": 1070468443, "lat": 39.2315311, "lon": -84.5489114}, {"type": "node", "id": 1070468473, "lat": 39.2322561, "lon": -84.5519807}, {"type": "node", "id": 1070468475, "lat": 39.2333062, "lon": -84.5455461}, {"type": "node", "id": 1070468487, "lat": 39.2316123, "lon": -84.5502283}, {"type": "node", "id": 1070468506, "lat": 39.2344657, "lon": -84.5473289}, {"type": "node", "id": 1070468532, "lat": 39.2288678, "lon": -84.5478302}, {"type": "node", "id": 1070468550, "lat": 39.2303752, "lon": -84.5536758}, {"type": "node", "id": 1070468560, "lat": 39.2298245, "lon": -84.5522019}, {"type": "node", "id": 1070468597, "lat": 39.2370101, "lon": -84.5484295}, {"type": "node", "id": 1070468599, "lat": 39.2296792, "lon": -84.5497485}, {"type": "node", "id": 1070468627, "lat": 39.2301109, "lon": -84.5490362}, {"type": "node", "id": 1070468763, "lat": 39.2361252, "lon": -84.549853}, {"type": "node", "id": 1070468781, "lat": 39.2301844, "lon": -84.5503333}, {"type": "node", "id": 1070468861, "lat": 39.2345924, "lon": -84.553442, "tags": {"highway": "turning_circle"}}, {"type": "node", "id": 1070468871, "lat": 39.2335618, "lon": -84.5487405}, {"type": "node", "id": 1070468883, "lat": 39.2316918, "lon": -84.5514458}, {"type": "node", "id": 1070468885, "lat": 39.2334183, "lon": -84.5461335}, {"type": "node", "id": 1070468922, "lat": 39.2332092, "lon": -84.5450052}, {"type": "node", "id": 1070468923, "lat": 39.2360537, "lon": -84.54852}, {"type": "node", "id": 1070468927, "lat": 39.2346002, "lon": -84.5499526}, {"type": "node", "id": 1070468928, "lat": 39.2329179, "lon": -84.5534634}, {"type": "node", "id": 1070468942, "lat": 39.2327849, "lon": -84.5524313}, {"type": "node", "id": 1070468946, "lat": 39.2320771, "lon": -84.5495399}, {"type": "node", "id": 1070468960, "lat": 39.2372084, "lon": -84.5514954}, {"type": "node", "id": 2090664473, "lat": 39.2429384, "lon": -84.5699347}, {"type": "node", "id": 2090685468, "lat": 39.2309821, "lon": -84.5483175}, {"type": "node", "id": 2090685561, "lat": 39.2310556, "lon": -84.5496201}, {"type": "node", "id": 2099429016, "lat": 39.2423788, "lon": -84.5494081}, {"type": "node", "id": 2099429044, "lat": 39.2415604, "lon": -84.5485927}, {"type": "node", "id": 2099429045, "lat": 39.241523, "lon": -84.5484747}, {"type": "node", "id": 2099429051, "lat": 39.2422251, "lon": -84.5489843}, {"type": "node", "id": 2099429094, "lat": 39.2381595, "lon": -84.5490206}, {"type": "node", "id": 2099429118, "lat": 39.2416892, "lon": -84.5487322}, {"type": "node", "id": 2099429140, "lat": 39.242142, "lon": -84.5489039}, {"type": "node", "id": 2099429142, "lat": 39.2423082, "lon": -84.5491077}, {"type": "node", "id": 2099429304, "lat": 39.2420548, "lon": -84.5488663}, {"type": "node", "id": 2099429309, "lat": 39.2345303, "lon": -84.5591553}, {"type": "node", "id": 2099429329, "lat": 39.2389251, "lon": -84.5476309}, {"type": "node", "id": 2099429361, "lat": 39.2324381, "lon": -84.5580141}, {"type": "node", "id": 2099429366, "lat": 39.241604, "lon": -84.5486652}, {"type": "node", "id": 2099429370, "lat": 39.2344885, "lon": -84.5590723}, {"type": "node", "id": 2099429390, "lat": 39.2389868, "lon": -84.5476254}, {"type": "node", "id": 2099429434, "lat": 39.2423498, "lon": -84.5492365}, {"type": "node", "id": 2099429438, "lat": 39.2414502, "lon": -84.5474076, "tags": {"highway": "traffic_signals"}}, {"type": "node", "id": 2099429473, "lat": 39.2424822, "lon": -84.5508493}, {"type": "node", "id": 2099447117, "lat": 39.2376021, "lon": -84.557656}, {"type": "node", "id": 2099447125, "lat": 39.2410757, "lon": -84.5474407}, {"type": "node", "id": 2099447177, "lat": 39.2376586, "lon": -84.5584614}, {"type": "node", "id": 2099447180, "lat": 39.2419573, "lon": -84.5488306}, {"type": "node", "id": 2099447211, "lat": 39.2376214, "lon": -84.5579298}, {"type": "node", "id": 2272264875, "lat": 39.2406752, "lon": -84.5474761}, {"type": "node", "id": 2272266140, "lat": 39.2427214, "lon": -84.547286}, {"type": "node", "id": 2272266142, "lat": 39.2406053, "lon": -84.5474823}, {"type": "node", "id": 2489440218, "lat": 39.2345372, "lon": -84.5493295, "tags": {"crossing": "zebra", "highway": "crossing"}}, {"type": "node", "id": 2489440220, "lat": 39.2335895, "lon": -84.5493148, "tags": {"crossing": "zebra", "highway": "crossing"}}, {"type": "node", "id": 2489440221, "lat": 39.23596, "lon": -84.5478964, "tags": {"crossing": "zebra", "highway": "crossing"}}, {"type": "node", "id": 2489440223, "lat": 39.2346057, "lon": -84.5493236, "tags": {"crossing": "zebra", "highway": "crossing"}}, {"type": "node", "id": 2489440224, "lat": 39.2344706, "lon": -84.5480283}, {"type": "node", "id": 2489440225, "lat": 39.233442, "lon": -84.5481116, "tags": {"crossing": "traffic_signals", "highway": "crossing"}}, {"type": "node", "id": 2489440227, "lat": 39.2415524, "lon": -84.5473982, "tags": {"crossing": "traffic_signals", "highway": "crossing"}}, {"type": "node", "id": 2489440228, "lat": 39.2345391, "lon": -84.5480223}, {"type": "node", "id": 2489440229, "lat": 39.2370607, "lon": -84.5492257, "tags": {"crossing": "zebra", "highway": "crossing"}}, {"type": "node", "id": 2489440231, "lat": 39.241457, "lon": -84.5475068, "tags": {"crossing": "traffic_signals", "highway": "crossing"}}, {"type": "node", "id": 2489440232, "lat": 39.2371234, "lon": -84.5491148, "tags": {"crossing": "zebra", "highway": "crossing"}}, {"type": "node", "id": 2489440233, "lat": 39.2345709, "lon": -84.5494245, "tags": {"crossing": "zebra", "highway": "crossing"}}, {"type": "node", "id": 2489440236, "lat": 39.2335365, "lon": -84.5482173, "tags": {"crossing": "traffic_signals", "highway": "crossing"}}, {"type": "node", "id": 2489440237, "lat": 39.2360946, "lon": -84.549301, "tags": {"crossing": "zebra", "highway": "crossing"}}, {"type": "node", "id": 2489440238, "lat": 39.2369866, "lon": -84.5491255, "tags": {"crossing": "zebra", "highway": "crossing"}}, {"type": "node", "id": 2489440240, "lat": 39.2336812, "lon": -84.549401, "tags": {"crossing": "zebra", "highway": "crossing"}}, {"type": "node", "id": 2489440241, "lat": 39.2360838, "lon": -84.5490976, "tags": {"crossing": "zebra", "highway": "crossing"}}, {"type": "node", "id": 2489440242, "lat": 39.2361514, "lon": -84.549193, "tags": {"crossing": "zebra", "highway": "crossing"}}, {"type": "node", "id": 2489440244, "lat": 39.2370486, "lon": -84.5490225, "tags": {"crossing": "zebra", "highway": "crossing"}}, {"type": "node", "id": 2489440245, "lat": 39.2360158, "lon": -84.5477832, "tags": {"crossing": "zebra", "highway": "crossing"}}, {"type": "node", "id": 2489440246, "lat": 39.2360331, "lon": -84.5492027, "tags": {"crossing": "zebra", "highway": "crossing"}}, {"type": "node", "id": 2489440248, "lat": 39.2335249, "lon": -84.5479979, "tags": {"crossing": "traffic_signals", "highway": "crossing"}}, {"type": "node", "id": 2489440249, "lat": 39.2369052, "lon": -84.5478162, "tags": {"crossing": "traffic_signals", "highway": "crossing"}}, {"type": "node", "id": 2489440250, "lat": 39.2335192, "lon": -84.5494145, "tags": {"crossing": "zebra", "highway": "crossing"}}, {"type": "node", "id": 2489440251, "lat": 39.2336165, "lon": -84.5480971, "tags": {"crossing": "traffic_signals", "highway": "crossing"}}, {"type": "node", "id": 2489440253, "lat": 39.2345611, "lon": -84.5492315, "tags": {"crossing": "zebra", "highway": "crossing"}}, {"type": "node", "id": 2489440254, "lat": 39.2344935, "lon": -84.5479114, "tags": {"crossing": "traffic_signals", "highway": "crossing"}}, {"type": "node", "id": 2489440255, "lat": 39.2345037, "lon": -84.548118, "tags": {"crossing": "traffic_signals", "highway": "crossing"}}, {"type": "node", "id": 2489447211, "lat": 39.2315025, "lon": -84.5483757, "tags": {"highway": "crossing"}}, {"type": "node", "id": 2489447212, "lat": 39.2301328, "lon": -84.5483834, "tags": {"crossing": "zebra", "highway": "crossing"}}, {"type": "node", "id": 2489447214, "lat": 39.2324199, "lon": -84.5481984, "tags": {"crossing": "traffic_signals", "highway": "crossing"}}, {"type": "node", "id": 2489447218, "lat": 39.2315744, "lon": -84.5496879, "tags": {"crossing": "zebra", "highway": "crossing"}}, {"type": "node", "id": 2489447222, "lat": 39.2289326, "lon": -84.5484028, "tags": {"crossing": "traffic_signals", "highway": "crossing"}}, {"type": "node", "id": 2489447225, "lat": 39.2290002, "lon": -84.5484982, "tags": {"crossing": "traffic_signals", "highway": "crossing"}}, {"type": "node", "id": 2489447229, "lat": 39.2325176, "lon": -84.5495018, "tags": {"crossing": "traffic_signals", "highway": "crossing"}}, {"type": "node", "id": 2489447230, "lat": 39.2316428, "lon": -84.5495774, "tags": {"crossing": "zebra", "highway": "crossing"}}, {"type": "node", "id": 2489447231, "lat": 39.233461, "lon": -84.5468929, "tags": {"crossing": "zebra", "highway": "crossing"}}, {"type": "node", "id": 2489447234, "lat": 39.2314327, "lon": -84.5470698, "tags": {"crossing": "zebra", "highway": "crossing"}}, {"type": "node", "id": 2489447237, "lat": 39.2325892, "lon": -84.5493891, "tags": {"crossing": "traffic_signals", "highway": "crossing"}}, {"type": "node", "id": 2489447238, "lat": 39.2314998, "lon": -84.5495883, "tags": {"crossing": "zebra", "highway": "crossing"}}, {"type": "node", "id": 2489447242, "lat": 39.2300797, "lon": -84.5484881, "tags": {"crossing": "zebra", "highway": "crossing"}}, {"type": "node", "id": 2489447243, "lat": 39.2331362, "lon": -84.5443928, "tags": {"crossing": "zebra", "highway": "crossing"}}, {"type": "node", "id": 2489447245, "lat": 39.228888, "lon": -84.5485085, "tags": {"crossing": "traffic_signals", "highway": "crossing"}}, {"type": "node", "id": 2489447247, "lat": 39.231431, "lon": -84.5482787, "tags": {"highway": "crossing"}}, {"type": "node", "id": 2489447250, "lat": 39.2326694, "lon": -84.5494886, "tags": {"crossing": "traffic_signals", "highway": "crossing"}}, {"type": "node", "id": 2489447252, "lat": 39.2289507, "lon": -84.548612, "tags": {"crossing": "traffic_signals", "highway": "crossing"}}, {"type": "node", "id": 2489447253, "lat": 39.2326009, "lon": -84.5481834, "tags": {"crossing": "traffic_signals", "highway": "crossing"}}, {"type": "node", "id": 2489447254, "lat": 39.2325197, "lon": -84.548311, "tags": {"crossing": "traffic_signals", "highway": "crossing"}}, {"type": "node", "id": 2489447260, "lat": 39.2326026, "lon": -84.5495933, "tags": {"crossing": "traffic_signals", "highway": "crossing"}}, {"type": "node", "id": 2489447264, "lat": 39.2315766, "lon": -84.5482666, "tags": {"highway": "crossing"}}, {"type": "node", "id": 2489447266, "lat": 39.2315614, "lon": -84.5494782, "tags": {"crossing": "zebra", "highway": "crossing"}}, {"type": "node", "id": 2489447269, "lat": 39.2314917, "lon": -84.5481746, "tags": {"highway": "crossing"}}, {"type": "node", "id": 2489447273, "lat": 39.2331543, "lon": -84.5445539, "tags": {"crossing": "zebra", "highway": "crossing"}}, {"type": "node", "id": 2519394699, "lat": 39.2327496, "lon": -84.5518457, "tags": {"crossing": "zebra", "highway": "crossing"}}, {"type": "node", "id": 2519394700, "lat": 39.2300942, "lon": -84.5497092, "tags": {"crossing": "zebra", "highway": "crossing"}}, {"type": "node", "id": 2519394702, "lat": 39.2301425, "lon": -84.5495901, "tags": {"crossing": "zebra", "highway": "crossing"}}, {"type": "node", "id": 2519394703, "lat": 39.2302103, "lon": -84.5496983, "tags": {"crossing": "zebra", "highway": "crossing"}}, {"type": "node", "id": 2519394706, "lat": 39.2330712, "lon": -84.5579566, "tags": {"crossing": "traffic_signals", "highway": "crossing"}}, {"type": "node", "id": 2519394710, "lat": 39.2282124, "lon": -84.5486916, "tags": {"highway": "crossing"}}, {"type": "node", "id": 2519394714, "lat": 39.2328345, "lon": -84.5520899, "tags": {"crossing": "zebra", "highway": "crossing"}}, {"type": "node", "id": 2519394715, "lat": 39.2331391, "lon": -84.5578754, "tags": {"crossing": "traffic_signals", "highway": "crossing"}}, {"type": "node", "id": 2523825214, "lat": 39.2377319, "lon": -84.5477387}, {"type": "node", "id": 2523825215, "lat": 39.2369782, "lon": -84.5479371, "tags": {"crossing": "traffic_signals", "highway": "crossing"}}, {"type": "node", "id": 2698264521, "lat": 39.2183129, "lon": -84.5558972, "tags": {"crossing": "traffic_signals", "highway": "crossing"}}, {"type": "node", "id": 2707213054, "lat": 39.229989, "lon": -84.5582383}, {"type": "node", "id": 2707225477, "lat": 39.2333393, "lon": -84.5610347}, {"type": "node", "id": 2707233010, "lat": 39.2333506, "lon": -84.5612172}, {"type": "node", "id": 2707233031, "lat": 39.2336188, "lon": -84.5653369, "tags": {"crossing": "traffic_signals", "highway": "crossing"}}, {"type": "node", "id": 2916061151, "lat": 39.2352377, "lon": -84.551878}, {"type": "node", "id": 2916078930, "lat": 39.2372181, "lon": -84.5516603, "tags": {"crossing": "zebra", "highway": "crossing"}}, {"type": "node", "id": 2952344198, "lat": 39.2186566, "lon": -84.5558632}, {"type": "node", "id": 5398204221, "lat": 39.2454181, "lon": -84.5470759}, {"type": "node", "id": 5398204222, "lat": 39.2451338, "lon": -84.5471015}, {"type": "node", "id": 5398204228, "lat": 39.2440722, "lon": -84.5471841, "tags": {"crossing": "traffic_signals", "highway": "crossing"}}, {"type": "node", "id": 5398204229, "lat": 39.2442659, "lon": -84.5471703}, {"type": "node", "id": 5398204231, "lat": 39.2429122, "lon": -84.5472655}, {"type": "node", "id": 5398204237, "lat": 39.2434738, "lon": -84.547227}, {"type": "node", "id": 5398204238, "lat": 39.2431909, "lon": -84.5472423}, {"type": "node", "id": 5398204255, "lat": 39.2415093, "lon": -84.5483649}, {"type": "node", "id": 5398204352, "lat": 39.2410469, "lon": -84.5474432}, {"type": "node", "id": 5398204353, "lat": 39.2394745, "lon": -84.5475823}, {"type": "node", "id": 5398204371, "lat": 39.2383973, "lon": -84.5476776}, {"type": "node", "id": 5398204376, "lat": 39.2381022, "lon": -84.5477037}, {"type": "node", "id": 5398204378, "lat": 39.2382547, "lon": -84.5476902}, {"type": "node", "id": 5398204379, "lat": 39.2374696, "lon": -84.5477636}, {"type": "node", "id": 5398204380, "lat": 39.2373131, "lon": -84.5477784}, {"type": "node", "id": 5398204385, "lat": 39.2361754, "lon": -84.5478778}, {"type": "node", "id": 5398204387, "lat": 39.2364953, "lon": -84.5478503}, {"type": "node", "id": 5398204388, "lat": 39.2361295, "lon": -84.547882}, {"type": "node", "id": 5398204392, "lat": 39.2366384, "lon": -84.5478381}, {"type": "node", "id": 5398204398, "lat": 39.235962, "lon": -84.5466628, "tags": {"crossing": "zebra", "highway": "crossing"}}, {"type": "node", "id": 5398204410, "lat": 39.2360079, "lon": -84.5476182}, {"type": "node", "id": 5398204415, "lat": 39.2353964, "lon": -84.5479429}, {"type": "node", "id": 5398204430, "lat": 39.2346563, "lon": -84.5480114}, {"type": "node", "id": 5398204431, "lat": 39.2349573, "lon": -84.5479836}, {"type": "node", "id": 5398204433, "lat": 39.235028, "lon": -84.5492878}, {"type": "node", "id": 5398204455, "lat": 39.2340313, "lon": -84.5480637}, {"type": "node", "id": 5398204471, "lat": 39.2330278, "lon": -84.548147}, {"type": "node", "id": 5398204508, "lat": 39.2320206, "lon": -84.5482307}, {"type": "node", "id": 5398204518, "lat": 39.2292842, "lon": -84.5484691}, {"type": "node", "id": 5398204520, "lat": 39.2284745, "lon": -84.5485421}, {"type": "node", "id": 5401545151, "lat": 39.2315382, "lon": -84.5490433}, {"type": "node", "id": 5401545154, "lat": 39.2315464, "lon": -84.5491984}, {"type": "node", "id": 5401545215, "lat": 39.233128, "lon": -84.544295}, {"type": "node", "id": 5401549526, "lat": 39.2332713, "lon": -84.5599416}, {"type": "node", "id": 5401549595, "lat": 39.2371505, "lon": -84.5506062}, {"type": "node", "id": 6051909494, "lat": 39.2330398, "lon": -84.5494563}, {"type": "node", "id": 6051909496, "lat": 39.2331918, "lon": -84.5494431}, {"type": "node", "id": 6051909499, "lat": 39.2333417, "lon": -84.54943}, {"type": "node", "id": 6051909506, "lat": 39.2282382, "lon": -84.5491335}, {"type": "node", "id": 6051909574, "lat": 39.2209281, "lon": -84.5556495, "tags": {"crossing": "marked", "highway": "crossing"}}, {"type": "node", "id": 6051909575, "lat": 39.2208175, "lon": -84.5556588, "tags": {"crossing": "marked", "highway": "crossing"}}, {"type": "node", "id": 6370270038, "lat": 39.2329533, "lon": -84.5550412}, {"type": "node", "id": 6699453659, "lat": 39.2334373, "lon": -84.5462816}, {"type": "node", "id": 6699453662, "lat": 39.2334503, "lon": -84.5464685}, {"type": "node", "id": 6859192263, "lat": 39.2189279, "lon": -84.5558363}, {"type": "node", "id": 6859192277, "lat": 39.2194344, "lon": -84.5557864}, {"type": "node", "id": 6947500353, "lat": 39.2337929, "lon": -84.5679113}, {"type": "node", "id": 6947500358, "lat": 39.2337364, "lon": -84.5668682}, {"type": "node", "id": 6947500359, "lat": 39.2337171, "lon": -84.5666063}, {"type": "node", "id": 6968675612, "lat": 39.2375068, "lon": -84.5563126}, {"type": "node", "id": 6971316536, "lat": 39.2375238, "lon": -84.5565525}, {"type": "node", "id": 6979361721, "lat": 39.2389772, "lon": -84.5593452}, {"type": "node", "id": 6987393028, "lat": 39.2329021, "lon": -84.5542604}, {"type": "node", "id": 7127897474, "lat": 39.2361343, "lon": -84.5500284}, {"type": "node", "id": 7127897484, "lat": 39.2373052, "lon": -84.553149}, {"type": "node", "id": 7128004957, "lat": 39.237538, "lon": -84.556752}, {"type": "node", "id": 7130358784, "lat": 39.2330539, "lon": -84.5565759}, {"type": "node", "id": 7130414886, "lat": 39.2330178, "lon": -84.5560253}, {"type": "node", "id": 7135393664, "lat": 39.2304244, "lon": -84.5545331}, {"type": "node", "id": 7135393668, "lat": 39.2308141, "lon": -84.5531286}, {"type": "node", "id": 7147693032, "lat": 39.2282468, "lon": -84.5485606}, {"type": "node", "id": 7151351815, "lat": 39.234104, "lon": -84.5713363}, {"type": "node", "id": 7154117109, "lat": 39.233834, "lon": -84.5684517}, {"type": "node", "id": 7180598423, "lat": 39.2430596, "lon": -84.573182}, {"type": "node", "id": 7203100703, "lat": 39.244481, "lon": -84.547155}, {"type": "node", "id": 7265313067, "lat": 39.2429584, "lon": -84.5679211}, {"type": "node", "id": 7265313073, "lat": 39.2431508, "lon": -84.5673671}, {"type": "node", "id": 7761035633, "lat": 39.2330234, "lon": -84.5561103}, {"type": "node", "id": 8000472804, "lat": 39.2304162, "lon": -84.5483614}, {"type": "node", "id": 8002067508, "lat": 39.2383401, "lon": -84.5476827}, {"type": "node", "id": 8002067516, "lat": 39.238013, "lon": -84.547712}, {"type": "node", "id": 8038454354, "lat": 39.2297928, "lon": -84.5570455}, {"type": "node", "id": 8038454355, "lat": 39.2299398, "lon": -84.5570125}, {"type": "node", "id": 8038454356, "lat": 39.229847, "lon": -84.556955}, {"type": "node", "id": 8038454358, "lat": 39.2297947, "lon": -84.5570269}, {"type": "node", "id": 8038454360, "lat": 39.2298283, "lon": -84.5571327}, {"type": "node", "id": 8038454361, "lat": 39.2299305, "lon": -84.5571079}, {"type": "node", "id": 8038454362, "lat": 39.2298605, "lon": -84.5571473}, {"type": "node", "id": 8038454363, "lat": 39.2299258, "lon": -84.5569835}, {"type": "node", "id": 8038454364, "lat": 39.2298234, "lon": -84.5569705}, {"type": "node", "id": 8038454366, "lat": 39.2297963, "lon": -84.5570794}, {"type": "node", "id": 8038454368, "lat": 39.229887, "lon": -84.5571452}, {"type": "node", "id": 8038454369, "lat": 39.2299423, "lon": -84.5570772}, {"type": "node", "id": 8038454370, "lat": 39.2298734, "lon": -84.556951}, {"type": "node", "id": 8038454371, "lat": 39.2299049, "lon": -84.5569624}, {"type": "node", "id": 8038454372, "lat": 39.2298052, "lon": -84.5569954}, {"type": "node", "id": 8038454374, "lat": 39.2298087, "lon": -84.5571097}, {"type": "node", "id": 8038454376, "lat": 39.2299113, "lon": -84.5571315}, {"type": "node", "id": 8082925094, "lat": 39.2340131, "lon": -84.5704063}, {"type": "node", "id": 8110522376, "lat": 39.2330103, "lon": -84.5559102}, {"type": "node", "id": 8169423456, "lat": 39.230758, "lon": -84.5521187}, {"type": "node", "id": 8169690476, "lat": 39.2374435, "lon": -84.5554198}, {"type": "node", "id": 8169755827, "lat": 39.2339518, "lon": -84.569786}, {"type": "node", "id": 8169755829, "lat": 39.2339018, "lon": -84.5692279}, {"type": "node", "id": 8169755835, "lat": 39.2339334, "lon": -84.5695909}, {"type": "node", "id": 8169923609, "lat": 39.2321321, "lon": -84.5495351}, {"type": "node", "id": 8169923616, "lat": 39.2334751, "lon": -84.5471365}, {"type": "node", "id": 8170232382, "lat": 39.2402188, "lon": -84.5475165}, {"type": "node", "id": 8170232389, "lat": 39.2400078, "lon": -84.5475351}, {"type": "node", "id": 8507769475, "lat": 39.235762, "lon": -84.5492256}, {"type": "node", "id": 8508738403, "lat": 39.2306161, "lon": -84.5496608}, {"type": "node", "id": 8508883655, "lat": 39.2398052, "lon": -84.547553}, {"type": "node", "id": 8670911659, "lat": 39.237265, "lon": -84.5524616}, {"type": "node", "id": 8670911669, "lat": 39.2354758, "lon": -84.5492499}, {"type": "node", "id": 8671391577, "lat": 39.2326382, "lon": -84.5501263}, {"type": "node", "id": 8671457196, "lat": 39.2293231, "lon": -84.5484651}, {"type": "node", "id": 8671457211, "lat": 39.2297752, "lon": -84.5484187}, {"type": "node", "id": 8671457216, "lat": 39.2300954, "lon": -84.5487636}, {"type": "node", "id": 8671517321, "lat": 39.2300854, "lon": -84.5485885}, {"type": "node", "id": 8671517325, "lat": 39.2298628, "lon": -84.5484097}, {"type": "node", "id": 8671517331, "lat": 39.2289658, "lon": -84.5488533}, {"type": "node", "id": 8671543599, "lat": 39.2323424, "lon": -84.5580228}, {"type": "node", "id": 8671620204, "lat": 39.2329739, "lon": -84.5553546}, {"type": "node", "id": 8671721324, "lat": 39.2314378, "lon": -84.5471648}, {"type": "node", "id": 8671721325, "lat": 39.2314476, "lon": -84.547349}, {"type": "node", "id": 8671721328, "lat": 39.2314557, "lon": -84.5474987}, {"type": "node", "id": 9016096621, "lat": 39.2404778, "lon": -84.5474936}, {"type": "node", "id": 9016096628, "lat": 39.2403003, "lon": -84.5475093}, {"type": "node", "id": 9028291987, "lat": 39.2287324, "lon": -84.5465737}, {"type": "node", "id": 9694808254, "lat": 39.2374278, "lon": -84.5477675}, {"type": "node", "id": 10593935792, "lat": 39.2409439, "lon": -84.5474523}, {"type": "way", "id": 19051411, "nodes": [197402971, 197402969, 307930780, 307930779, 307930778, 307930777, 197571897], "tags": {"destination": "Ronald Reagan Highway", "destination:ref": "SR 126 West", "destination:ref:wikidata": "Q2491937", "highway": "motorway_link", "lanes": "1", "oneway": "yes", "tiger:cfcc": "A63", "tiger:county": "Hamilton, OH", "tiger:reviewed": "no"}}, {"type": "way", "id": 19051919, "nodes": [197409121, 197409123], "tags": {"highway": "residential", "name": "South Lynndale Court", "tiger:cfcc": "A41", "tiger:county": "Hamilton, OH", "tiger:name_base": "Lynndale", "tiger:name_direction_prefix": "S", "tiger:name_type": "Ct", "tiger:reviewed": "no", "tiger:zip_left": "45231", "tiger:zip_right": "45231"}}, {"type": "way", "id": 19053869, "nodes": [197442691, 197442692], "tags": {"highway": "residential", "name": "Harding Avenue", "tiger:cfcc": "A41", "tiger:county": "Hamilton, OH", "tiger:name_base": "Harding", "tiger:name_type": "Ave", "tiger:reviewed": "no", "tiger:zip_left": "45231", "tiger:zip_right": "45231"}}, {"type": "way", "id": 19054238, "nodes": [197448748, 197448782, 6979361721, 197448783, 197448784, 197448785, 197448787, 197448788, 197448789, 197448791, 197448792, 197448794, 197448796, 197448798, 197448800, 197448802, 197448804, 197448806, 197448808, 197448810, 197448812, 197448815, 197448817, 197448819, 197448821, 197448823, 197448825, 197448827, 197448829, 197448831, 197448833, 197448835, 197448837, 197448839, 197448841, 197448842, 7265313073, 197448843, 197448845, 7265313067, 197448848, 197448850, 197448852, 197426517, 197448853, 2090664473, 197448856, 197448858, 197448860, 7180598423, 197448862, 197448865], "tags": {"highway": "unclassified", "name": "Adams Road", "tiger:cfcc": "A41", "tiger:county": "Hamilton, OH", "tiger:name_base": "Adams", "tiger:name_type": "Rd", "tiger:reviewed": "no", "tiger:zip_left": "45231"}}, {"type": "way", "id": 19054457, "nodes": [197452746, 197452748, 197452750], "tags": {"highway": "residential", "name": "Kinney Avenue", "tiger:cfcc": "A41", "tiger:county": "Hamilton, OH", "tiger:name_base": "Kinney", "tiger:name_type": "Ave", "tiger:reviewed": "no"}}, {"type": "way", "id": 19056030, "nodes": [197479101, 2489447242, 8671517321, 8671457216, 1070468627, 2519394702, 197479103, 1070468781, 197479105, 197479106, 1070468366, 197479108, 1070468550, 7135393664, 197479110, 197479112, 197436128, 197479114], "tags": {"highway": "residential", "name": "Stevens Avenue", "tiger:cfcc": "A41", "tiger:county": "Hamilton, OH", "tiger:name_base": "Stevens", "tiger:name_type": "Ave", "tiger:reviewed": "no", "tiger:zip_left": "45231", "tiger:zip_right": "45231"}}, {"type": "way", "id": 19058132, "nodes": [197506366, 197506367, 197506368, 197506370, 197506371, 197506372, 197506374, 197506376, 197506378, 197506380, 197506382, 197506384, 197506386, 197506388, 197506390, 197506392, 197506394, 197506396, 197506398, 197448792], "tags": {"highway": "residential", "name": "Ranchill Drive", "tiger:cfcc": "A41", "tiger:county": "Hamilton, OH", "tiger:name_base": "Ranchill", "tiger:name_type": "Dr", "tiger:reviewed": "no", "tiger:zip_left": "45231", "tiger:zip_right": "45231"}}, {"type": "way", "id": 19058932, "nodes": [197514615, 197514618, 197514621, 197514623, 197514626, 197514628], "tags": {"highway": "residential", "name": "Compton Lake Drive", "tiger:cfcc": "A41", "tiger:county": "Hamilton, OH", "tiger:name_base": "Compton Lake", "tiger:name_type": "Dr", "tiger:reviewed": "no", "tiger:zip_left": "45231", "tiger:zip_right": "45231"}}, {"type": "way", "id": 19059660, "nodes": [197418751, 197524191, 197524194, 197524196, 197524198], "tags": {"highway": "residential", "name": "Lincoln Avenue", "tiger:cfcc": "A41", "tiger:county": "Hamilton, OH", "tiger:name_base": "Lincoln", "tiger:name_type": "Ave", "tiger:reviewed": "no", "tiger:zip_left": "45231", "tiger:zip_right": "45231"}}, {"type": "way", "id": 19059901, "nodes": [197527078, 2519394714, 2916061151], "tags": {"highway": "residential", "name": "Werner Avenue", "tiger:cfcc": "A41", "tiger:county": "Hamilton, OH", "tiger:name_base": "Werner", "tiger:name_type": "Ave", "tiger:reviewed": "no", "tiger:zip_left": "45231", "tiger:zip_right": "45231"}}, {"type": "way", "id": 19059903, "nodes": [197527085, 197527086, 197527087, 197527088, 197527089, 197527090, 197527091, 197527092, 1070468560, 197479106, 8169423456, 197452788, 1070468473, 197527093], "tags": {"highway": "residential", "name": "Werner Avenue", "tiger:cfcc": "A41", "tiger:county": "Hamilton, OH", "tiger:name_base": "Werner", "tiger:name_type": "Ave", "tiger:reviewed": "no", "tiger:zip_left": "45231", "tiger:zip_right": "45231"}}, {"type": "way", "id": 19060068, "nodes": [197528646, 197528648], "tags": {"highway": "residential", "name": "Fondulac Drive", "tiger:cfcc": "A41", "tiger:county": "Hamilton, OH", "tiger:name_base": "Fondulac", "tiger:name_type": "Dr", "tiger:reviewed": "no", "tiger:zip_left": "45231", "tiger:zip_right": "45231"}}, {"type": "way", "id": 19061617, "nodes": [197452786, 197543334, 197543337], "tags": {"highway": "residential", "name": "Phoenix Avenue", "tiger:cfcc": "A41", "tiger:county": "Hamilton, OH", "tiger:name_base": "Phoenix", "tiger:name_type": "Ave", "tiger:reviewed": "no", "tiger:zip_left": "45231", "tiger:zip_right": "45231"}}, {"type": "way", "id": 19061624, "nodes": [197543436, 197543439], "tags": {"highway": "residential", "name": "Cedar Avenue", "tiger:cfcc": "A41", "tiger:county": "Hamilton, OH", "tiger:name_base": "Cedar", "tiger:name_type": "Ave", "tiger:reviewed": "no", "tiger:zip_left": "45231", "tiger:zip_right": "45231"}}, {"type": "way", "id": 19062457, "nodes": [197557418, 197557420], "tags": {"highway": "residential", "name": "Lexa Court", "tiger:cfcc": "A41", "tiger:county": "Hamilton, OH", "tiger:name_base": "Lexa", "tiger:name_type": "Ct", "tiger:reviewed": "no", "tiger:zip_left": "45231", "tiger:zip_right": "45231"}}, {"type": "way", "id": 19063351, "nodes": [373775827, 373775788, 197572264, 197572266, 197572268, 197572270, 197409121, 197572272, 197572274, 197572276, 197479112, 197572278], "tags": {"highway": "residential", "name": "Park Avenue", "tiger:cfcc": "A41", "tiger:county": "Hamilton, OH", "tiger:name_base": "Park", "tiger:name_type": "Ave", "tiger:reviewed": "no", "tiger:zip_left": "45231", "tiger:zip_right": "45231"}}, {"type": "way", "id": 19063483, "nodes": [197574164, 197574166, 197574168, 197528646, 197574170, 197574172, 197574174, 197574176, 197574178, 197574180, 197574182, 197574184, 197574186, 197574188, 197574190, 197574192, 197574194, 197574196, 197574198, 197574200, 197574203, 197574204, 197574206, 197574208, 197574210, 197448748], "tags": {"highway": "residential", "name": "Tag Drive", "tiger:cfcc": "A41", "tiger:county": "Hamilton, OH", "tiger:name_base": "Tag", "tiger:name_type": "Dr", "tiger:reviewed": "no", "tiger:zip_left": "45231", "tiger:zip_right": "45231"}}, {"type": "way", "id": 19063531, "nodes": [197574856, 197574858, 1070468212, 197479108, 7135393668, 197574860, 197452746], "tags": {"highway": "residential", "name": "Maple Avenue", "tiger:cfcc": "A41", "tiger:county": "Hamilton, OH", "tiger:name_base": "Maple", "tiger:name_type": "Ave", "tiger:reviewed": "no", "tiger:zip_left": "45231", "tiger:zip_right": "45231"}}, {"type": "way", "id": 19064089, "nodes": [197505104, 2519394710, 6051909506, 197584055, 197527087], "tags": {"highway": "residential", "name": "Kemper Avenue", "tiger:cfcc": "A41", "tiger:county": "Hamilton, OH", "tiger:name_base": "Kemper", "tiger:name_type": "Ave", "tiger:reviewed": "no", "tiger:zip_left": "45231", "tiger:zip_right": "45231"}}, {"type": "way", "id": 19064920, "nodes": [197448744, 197596470, 197596471, 197596472, 197596474, 197557418, 197407524], "tags": {"highway": "residential", "name": "Duvall Place", "tiger:cfcc": "A41", "tiger:county": "Hamilton, OH", "tiger:name_base": "Duvall", "tiger:name_type": "Pl", "tiger:reviewed": "no", "tiger:zip_left": "45231", "tiger:zip_right": "45231"}}, {"type": "way", "id": 19065173, "nodes": [197601067, 2698264521, 2952344198, 6859192263, 197601069, 6859192277, 6051909575, 197601072, 6051909574, 197473032, 197601074, 197423688, 197601077, 197601079, 197601081, 197601083, 197601084, 197422286, 197601087, 373775827], "tags": {"highway": "residential", "name": "La Boiteaux Avenue", "tiger:cfcc": "A41", "tiger:county": "Hamilton, OH", "tiger:name_base": "La Boiteaux", "tiger:name_type": "Ave", "tiger:reviewed": "no", "tiger:zip_left": "45231", "tiger:zip_right": "45231"}}, {"type": "way", "id": 19065980, "nodes": [197572272, 197612872], "tags": {"highway": "residential", "name": "North Lynndale Court", "tiger:cfcc": "A41", "tiger:county": "Hamilton, OH", "tiger:name_base": "Lynndale", "tiger:name_direction_prefix": "N", "tiger:name_type": "Ct", "tiger:reviewed": "no", "tiger:zip_left": "45231", "tiger:zip_right": "45231"}}, {"type": "way", "id": 19066842, "nodes": [197448738, 2489440238, 2489440242, 197624004, 2489440246, 8507769475, 8670911669, 5398204433, 2489440223, 197418749, 2489440218, 197543436, 2489440240, 197497829, 2489440250, 6051909499, 6051909496, 6051909494, 2489447250, 197602011], "tags": {"highway": "residential", "name": "Harrison Avenue", "oneway": "no", "tiger:cfcc": "A41", "tiger:county": "Hamilton, OH", "tiger:name_base": "Harrison", "tiger:name_type": "Ave", "tiger:reviewed": "no", "tiger:zip_left": "45231", "tiger:zip_right": "45231"}}, {"type": "way", "id": 19069096, "nodes": [197640117, 197640119, 197640121, 2707213054], "tags": {"highway": "residential", "name": "Forest Avenue", "sidewalk": "no", "tiger:cfcc": "A41", "tiger:county": "Hamilton, OH", "tiger:name_base": "Forest", "tiger:name_type": "Ave", "tiger:reviewed": "no", "tiger:zip_left": "45231", "tiger:zip_right": "45231"}}, {"type": "way", "id": 19070180, "nodes": [197654929, 197654931, 197416146, 5398204398, 1070468415, 5398204410, 2489440245, 197505113, 1070468923, 2489440241, 197624004, 2489440237, 1070468763, 7127897474, 197654933, 197654935, 197654937, 197524198], "tags": {"highway": "residential", "name": "Hastings Avenue", "tiger:cfcc": "A41", "tiger:county": "Hamilton, OH", "tiger:name_base": "Hastings", "tiger:name_type": "Ave", "tiger:reviewed": "no", "tiger:zip_left": "45231", "tiger:zip_right": "45231"}}, {"type": "way", "id": 19072007, "nodes": [197527090, 197574858, 1070468085, 197442691, 197678897, 197572276], "tags": {"highway": "residential", "name": "Madison Avenue", "tiger:cfcc": "A41", "tiger:county": "Hamilton, OH", "tiger:name_base": "Madison", "tiger:name_type": "Ave", "tiger:reviewed": "no", "tiger:zip_left": "45231", "tiger:zip_right": "45231"}}, {"type": "way", "id": 19072011, "nodes": [197572274, 197678929, 197640119], "tags": {"highway": "residential", "name": "Madison Avenue", "tiger:cfcc": "A41", "tiger:county": "Hamilton, OH", "tiger:name_base": "Madison", "tiger:name_type": "Ave", "tiger:reviewed": "no", "tiger:zip_left": "45231", "tiger:zip_right": "45231"}}, {"type": "way", "id": 19072012, "nodes": [197624001, 197527091], "tags": {"highway": "residential", "name": "Madison Avenue", "tiger:cfcc": "A41", "tiger:county": "Hamilton, OH", "tiger:name_base": "Madison", "tiger:name_type": "Ave", "tiger:reviewed": "no", "tiger:zip_left": "45231", "tiger:zip_right": "45231"}}, {"type": "way", "id": 19072014, "nodes": [197429964, 197485936, 197520887, 9028291987, 197416132, 1070468532, 2489447222, 197505106, 2489447252, 8671517331, 197623999], "tags": {"highway": "residential", "name": "Madison Avenue", "tiger:cfcc": "A41", "tiger:county": "Hamilton, OH", "tiger:name_base": "Madison", "tiger:name_type": "Ave", "tiger:reviewed": "no", "tiger:zip_left": "45231", "tiger:zip_right": "45231"}}, {"type": "way", "id": 28043223, "nodes": [307933255, 307933232], "tags": {"bridge": "yes", "hgv": "designated", "hgv:national_network": "yes", "highway": "motorway", "lanes": "2", "layer": "1", "maxspeed": "65 mph", "name": "Ronald Reagan Cross County Highway", "old_ref": "RR", "old_ref:fap": "2", "oneway": "yes", "ref": "SR 126", "source:hgv:national_network": "Title 23: Highways Part 658 http://ecfr.gpoaccess.gov/cgi/t/text/text-idx?c=ecfr&rgn=div5&view=text&node=23:1.0.1.7.33&idno=23", "source:old_ref:fap": "ODOT http://www.dot.state.oh.us/Divisions/Planning/TechServ/prod_services/Pages/RI06.aspx http://www.dot.state.oh.us/Divisions/ContractAdmin/Contracts/Pages/NHS-FAP.aspx", "tiger:cfcc": "A31", "tiger:county": "Hamilton, OH", "tiger:name_base": "Ronald Reagan Cross County Hwy", "tiger:name_base_1": "State Route 126", "tiger:reviewed": "no", "tiger:zip_left": "45231", "tiger:zip_right": "45231"}}, {"type": "way", "id": 28043225, "nodes": [307933232, 197571914, 197571908, 197571906, 197571904, 197571902, 197571900, 197571898, 197571897, 197571895], "tags": {"hgv": "designated", "hgv:national_network": "yes", "highway": "motorway", "lanes": "2", "maxspeed": "65 mph", "name": "Ronald Reagan Cross County Highway", "old_ref": "RR", "old_ref:fap": "2", "oneway": "yes", "ref": "SR 126", "source:hgv:national_network": "Title 23: Highways Part 658 http://ecfr.gpoaccess.gov/cgi/t/text/text-idx?c=ecfr&rgn=div5&view=text&node=23:1.0.1.7.33&idno=23", "source:old_ref:fap": "ODOT http://www.dot.state.oh.us/Divisions/Planning/TechServ/prod_services/Pages/RI06.aspx http://www.dot.state.oh.us/Divisions/ContractAdmin/Contracts/Pages/NHS-FAP.aspx", "tiger:cfcc": "A31", "tiger:county": "Hamilton, OH", "tiger:name_base": "Ronald Reagan Cross County Hwy", "tiger:name_base_1": "State Route 126", "tiger:reviewed": "no", "tiger:zip_left": "45231", "tiger:zip_right": "45231"}}, {"type": "way", "id": 28043226, "nodes": [197571895, 197571893, 373775998, 197571887, 197571886], "tags": {"bridge": "yes", "hgv": "designated", "hgv:national_network": "yes", "highway": "motorway", "lanes": "2", "layer": "1", "maxspeed": "65 mph", "name": "Ronald Reagan Cross County Highway", "old_ref": "RR", "old_ref:fap": "2", "oneway": "yes", "ref": "SR 126", "source:hgv:national_network": "Title 23: Highways Part 658 http://ecfr.gpoaccess.gov/cgi/t/text/text-idx?c=ecfr&rgn=div5&view=text&node=23:1.0.1.7.33&idno=23", "source:old_ref:fap": "ODOT http://www.dot.state.oh.us/Divisions/Planning/TechServ/prod_services/Pages/RI06.aspx http://www.dot.state.oh.us/Divisions/ContractAdmin/Contracts/Pages/NHS-FAP.aspx", "tiger:cfcc": "A31", "tiger:county": "Hamilton, OH", "tiger:name_base": "Ronald Reagan Cross County Hwy", "tiger:name_base_1": "State Route 126", "tiger:reviewed": "no", "tiger:zip_left": "45231", "tiger:zip_right": "45231"}}, {"type": "way", "id": 28043254, "nodes": [197571886, 197571884, 197571880, 197571879, 197571877, 197571873, 197571869, 197571865, 197571864, 197571863, 197571861, 197571859, 197571857, 197571855, 197571853, 197571851, 197571847, 197571844, 197571841, 197571839, 197571837, 197571835, 197571833, 197571831, 197571829, 197571827, 197571825, 197571823, 197571821, 197571819, 197571817, 197571815, 373778570, 197571813, 197571811, 197571807, 197571798, 197571796, 197571794, 197571792, 197571790, 197571788, 197571786, 373781729, 197571784, 197571782, 307933387], "tags": {"hgv": "designated", "hgv:national_network": "yes", "highway": "motorway", "lanes": "2", "maxspeed": "65 mph", "name": "Ronald Reagan Cross County Highway", "old_ref": "RR", "old_ref:fap": "2", "oneway": "yes", "ref": "SR 126", "source:hgv:national_network": "Title 23: Highways Part 658 http://ecfr.gpoaccess.gov/cgi/t/text/text-idx?c=ecfr&rgn=div5&view=text&node=23:1.0.1.7.33&idno=23", "source:old_ref:fap": "ODOT http://www.dot.state.oh.us/Divisions/Planning/TechServ/prod_services/Pages/RI06.aspx http://www.dot.state.oh.us/Divisions/ContractAdmin/Contracts/Pages/NHS-FAP.aspx", "tiger:cfcc": "A31", "tiger:county": "Hamilton, OH", "tiger:name_base": "Ronald Reagan Cross County Hwy", "tiger:name_base_1": "State Route 126", "tiger:reviewed": "no", "tiger:zip_left": "45231", "tiger:zip_right": "45231"}}, {"type": "way", "id": 33114262, "nodes": [373776657, 373771618, 373771619, 373776639], "tags": {"bridge": "yes", "hgv": "designated", "hgv:national_network": "yes", "highway": "motorway", "lanes": "2", "layer": "1", "maxspeed": "65 mph", "name": "Ronald Reagan Cross County Highway", "old_ref": "RR", "old_ref:fap": "2", "oneway": "yes", "ref": "SR 126", "source:hgv:national_network": "Title 23: Highways Part 658 http://ecfr.gpoaccess.gov/cgi/t/text/text-idx?c=ecfr&rgn=div5&view=text&node=23:1.0.1.7.33&idno=23", "source:old_ref:fap": "ODOT http://www.dot.state.oh.us/Divisions/Planning/TechServ/prod_services/Pages/RI06.aspx http://www.dot.state.oh.us/Divisions/ContractAdmin/Contracts/Pages/NHS-FAP.aspx", "tiger:cfcc": "A31", "tiger:county": "Hamilton, OH", "tiger:name_base": "Ronald Reagan Cross County Hwy", "tiger:name_base_1": "State Route 126", "tiger:reviewed": "no", "tiger:zip_left": "45231", "tiger:zip_right": "45231"}}, {"type": "way", "id": 33114376, "nodes": [373779995, 373779915, 373779916, 373781740, 373779919, 373779920, 373779921, 373779280, 373779281, 373779282, 373779283, 373779284, 373779285, 373778458, 373778581, 373778461, 373778462, 373778463, 373778464, 373778467, 373778468, 373778470, 373778471, 373778472, 373778474, 373778475, 373778476, 373771611, 373771614, 373771615, 373771616, 373771617, 373776657], "tags": {"hgv": "designated", "hgv:national_network": "yes", "highway": "motorway", "lanes": "2", "maxspeed": "65 mph", "name": "Ronald Reagan Cross County Highway", "old_ref": "RR", "old_ref:fap": "2", "oneway": "yes", "ref": "SR 126", "source:hgv:national_network": "Title 23: Highways Part 658 http://ecfr.gpoaccess.gov/cgi/t/text/text-idx?c=ecfr&rgn=div5&view=text&node=23:1.0.1.7.33&idno=23", "source:old_ref:fap": "ODOT http://www.dot.state.oh.us/Divisions/Planning/TechServ/prod_services/Pages/RI06.aspx http://www.dot.state.oh.us/Divisions/ContractAdmin/Contracts/Pages/NHS-FAP.aspx", "tiger:cfcc": "A31", "tiger:county": "Hamilton, OH", "tiger:name_base": "Ronald Reagan Cross County Hwy", "tiger:name_base_1": "State Route 126", "tiger:reviewed": "no", "tiger:zip_left": "45231", "tiger:zip_right": "45231"}}, {"type": "way", "id": 92202606, "nodes": [197510434, 1070468928, 1070468352, 1070468861], "tags": {"highway": "residential"}}, {"type": "way", "id": 199958771, "nodes": [2099429438, 2489440231, 5398204255], "tags": {"change:backward": "no", "highway": "unclassified", "lanes": "3", "lanes:backward": "2", "lanes:forward": "1", "turn:lanes:backward": "left|right"}}, {"type": "way", "id": 199958788, "nodes": [197514628, 2099429370], "tags": {"highway": "residential", "name": "Compton Lake Drive", "tiger:cfcc": "A41", "tiger:county": "Hamilton, OH", "tiger:name_base": "Compton Lake", "tiger:name_type": "Dr", "tiger:reviewed": "no", "tiger:zip_left": "45231", "tiger:zip_right": "45231"}}, {"type": "way", "id": 199958830, "nodes": [197514631, 197514633, 197514635, 197514638, 197514640, 197407522, 197514642, 197514643, 197514645, 2099429309, 2099429370, 197514631], "tags": {"area": "no", "highway": "residential", "name": "Compton Lake Drive", "tiger:cfcc": "A41", "tiger:county": "Hamilton, OH", "tiger:name_base": "Compton Lake", "tiger:name_type": "Dr", "tiger:reviewed": "no", "tiger:zip_left": "45231", "tiger:zip_right": "45231"}}, {"type": "way", "id": 199958833, "nodes": [197514628, 197514645], "tags": {"highway": "residential", "name": "Compton Lake Drive", "tiger:cfcc": "A41", "tiger:county": "Hamilton, OH", "tiger:name_base": "Compton Lake", "tiger:name_type": "Dr", "tiger:reviewed": "no", "tiger:zip_left": "45231", "tiger:zip_right": "45231"}}, {"type": "way", "id": 217920698, "nodes": [197448738, 2489440232, 2099429094], "tags": {"highway": "residential", "name": "Harrison Avenue", "tiger:cfcc": "A41", "tiger:county": "Hamilton, OH", "tiger:name_base": "Harrison", "tiger:name_type": "Ave", "tiger:reviewed": "no", "tiger:zip_left": "45231", "tiger:zip_right": "45231"}}, {"type": "way", "id": 217920699, "nodes": [197505109, 2489447253, 5398204471, 2489440225, 197497827, 2489440251, 5398204455, 2489440224, 197418748], "tags": {"hgv": "designated", "hgv:national_network": "yes", "highway": "primary", "name": "Hamilton Avenue", "old_ref:fap": "6", "ref": "US 127", "source:hgv:national_network": "Title 23: Highways Part 658 http://ecfr.gpoaccess.gov/cgi/t/text/text-idx?c=ecfr&rgn=div5&view=text&node=23:1.0.1.7.33&idno=23", "source:old_ref:fap": "ODOT http://www.dot.state.oh.us/Divisions/Planning/TechServ/prod_services/Pages/RI06.aspx http://www.dot.state.oh.us/Divisions/ContractAdmin/Contracts/Pages/NHS-FAP.aspx", "tiger:cfcc": "A21", "tiger:county": "Hamilton, OH", "tiger:name_base": "Hamilton", "tiger:name_base_1": "United States Highway 127", "tiger:name_type": "Ave", "tiger:reviewed": "no", "tiger:zip_left": "45231", "tiger:zip_right": "45231"}}, {"type": "way", "id": 217920700, "nodes": [197448736, 2523825215, 1070468597], "tags": {"change:backward": "no", "highway": "residential", "lanes": "3", "lanes:backward": "2", "lanes:forward": "1", "name": "Adams Road", "oneway": "no", "tiger:cfcc": "A41", "tiger:county": "Hamilton, OH", "tiger:name_base": "Adams", "tiger:name_type": "Rd", "tiger:reviewed": "no", "tiger:zip_left": "45231", "tiger:zip_right": "45231", "turn:lanes:backward": "left|through;right"}}, {"type": "way", "id": 217920703, "nodes": [197602011, 2489447260, 8671391577, 197602013, 2519394699, 197527093, 197527078, 1070468942, 197574866, 197510434, 6987393028, 6370270038, 8671620204, 8110522376, 7130414886, 7761035633, 7130358784, 2519394715, 197602015, 197602017, 373775206, 197514615, 197602019, 5401549526, 2707225477, 2707233010, 197602021, 197506366, 373775207, 197602023, 2707233031, 197522548, 197602025, 6947500359, 6947500358, 197602027, 197602029, 197602031, 6947500353, 197602033, 7154117109, 8169755829, 8169755835, 197602035, 8169755827, 197426464, 8082925094, 7151351815, 197602037, 197602039, 197602041, 197602043, 197602045, 197602047, 197602049, 197602051, 197602053, 197602055, 197602057, 197602059, 197602061, 197602063, 197602065, 197602067, 197602069, 197602072], "tags": {"highway": "tertiary", "lanes": "2", "name": "Compton Road", "oneway": "no", "tiger:cfcc": "A41", "tiger:county": "Hamilton, OH", "tiger:name_base": "Compton", "tiger:name_type": "Rd", "tiger:reviewed": "no", "tiger:zip_left": "45231", "tiger:zip_right": "45231"}}, {"type": "way", "id": 217920704, "nodes": [2099429438, 2489440227, 197505121], "tags": {"change:backward": "no", "hgv": "designated", "hgv:national_network": "yes", "highway": "primary", "lanes": "4", "lanes:backward": "3", "lanes:forward": "1", "name": "Hamilton Avenue", "old_ref:fap": "6", "oneway": "no", "ref": "US 127", "source:hgv:national_network": "Title 23: Highways Part 658 http://ecfr.gpoaccess.gov/cgi/t/text/text-idx?c=ecfr&rgn=div5&view=text&node=23:1.0.1.7.33&idno=23", "source:old_ref:fap": "ODOT http://www.dot.state.oh.us/Divisions/Planning/TechServ/prod_services/Pages/RI06.aspx http://www.dot.state.oh.us/Divisions/ContractAdmin/Contracts/Pages/NHS-FAP.aspx", "tiger:cfcc": "A21", "tiger:county": "Hamilton, OH", "tiger:name_base": "Hamilton", "tiger:name_base_1": "United States Highway 127", "tiger:name_type": "Ave", "tiger:reviewed": "no", "tiger:zip_left": "45231", "tiger:zip_right": "45231", "turn:lanes:backward": "left||right"}}, {"type": "way", "id": 217920705, "nodes": [197602011, 2489447229, 8169923609, 1070468946, 2489447230, 197452783, 2489447238, 197624003, 2090685561, 8508738403, 1070468294, 2519394703, 197479103, 2519394700, 1070468599, 197624001, 197623999, 197584055], "tags": {"highway": "residential", "name": "Harrison Avenue", "oneway": "no", "tiger:cfcc": "A41", "tiger:county": "Hamilton, OH", "tiger:name_base": "Harrison", "tiger:name_type": "Ave", "tiger:reviewed": "no", "tiger:zip_left": "45231", "tiger:zip_right": "45231"}}, {"type": "way", "id": 217920709, "nodes": [197602011, 2489447237, 1070467934, 2489447254, 197505109], "tags": {"highway": "tertiary", "lanes": "2", "name": "Compton Road", "oneway": "no", "tiger:cfcc": "A41", "tiger:county": "Hamilton, OH", "tiger:name_base": "Compton", "tiger:name_type": "Rd", "tiger:reviewed": "no", "tiger:zip_left": "45231", "tiger:zip_right": "45231"}}, {"type": "way", "id": 217920710, "nodes": [197448738, 2489440229, 5401549595], "tags": {"highway": "residential", "name": "Adams Road", "tiger:cfcc": "A41", "tiger:county": "Hamilton, OH", "tiger:name_base": "Adams", "tiger:name_type": "Rd", "tiger:reviewed": "no", "tiger:zip_left": "45231", "tiger:zip_right": "45231"}}, {"type": "way", "id": 241255496, "nodes": [197429969, 1070468438, 5401545215, 2489447243, 197485952, 2489447273, 197497815, 1070468922, 197497817, 1070468475, 1070468885, 197497819, 6699453659, 197497821, 6699453662, 197497825, 197416139, 2489447231, 8169923616, 1070468219, 2489440248, 197497827, 2489440236, 1070468871, 2489440220, 197497829], "tags": {"highway": "residential", "name": "McMakin Avenue", "tiger:cfcc": "A41", "tiger:county": "Hamilton, OH", "tiger:name_base": "McMakin", "tiger:name_type": "Ave", "tiger:reviewed": "no", "tiger:zip_left": "45231", "tiger:zip_right": "45231"}}, {"type": "way", "id": 244646052, "nodes": [197416135, 2489447234, 8671721324, 8671721325, 8671721328, 1070468104, 2489447269, 197452781, 2489447211, 1070468443, 5401545151, 5401545154, 2489447266, 197452783, 2489447218, 1070468487, 197452786, 1070468883, 197452788, 197452790, 1070468016, 197452746], "tags": {"highway": "residential", "name": "Kinney Avenue", "tiger:cfcc": "A41", "tiger:county": "Hamilton, OH", "tiger:name_base": "Kinney", "tiger:name_type": "Ave", "tiger:reviewed": "no"}}, {"type": "way", "id": 265075087, "nodes": [2707213054, 197479114, 197640123, 8671543599, 2099429361, 2519394706, 197602015], "tags": {"highway": "residential", "name": "Forest Avenue", "sidewalk": "both", "tiger:cfcc": "A41", "tiger:county": "Hamilton, OH", "tiger:name_base": "Forest", "tiger:name_type": "Ave", "tiger:reviewed": "no", "tiger:zip_left": "45231", "tiger:zip_right": "45231"}}, {"type": "way", "id": 559732710, "nodes": [5398204222, 197505136, 5398204221], "tags": {"bridge": "yes", "hgv": "designated", "hgv:national_network": "yes", "highway": "primary", "lanes": "3", "lanes:backward": "1", "lanes:forward": "1", "layer": "1", "name": "Hamilton Avenue", "old_ref:fap": "6", "ref": "US 127", "source:hgv:national_network": "Title 23: Highways Part 658 http://ecfr.gpoaccess.gov/cgi/t/text/text-idx?c=ecfr&rgn=div5&view=text&node=23:1.0.1.7.33&idno=23", "source:old_ref:fap": "ODOT http://www.dot.state.oh.us/Divisions/Planning/TechServ/prod_services/Pages/RI06.aspx http://www.dot.state.oh.us/Divisions/ContractAdmin/Contracts/Pages/NHS-FAP.aspx", "turn:lanes:both_ways": "left"}}, {"type": "way", "id": 559732713, "nodes": [5398204229, 7203100703, 197505135, 5398204222], "tags": {"hgv": "designated", "hgv:national_network": "yes", "highway": "primary", "lanes": "3", "lanes:backward": "1", "lanes:both_ways": "1", "lanes:forward": "1", "name": "Hamilton Avenue", "old_ref:fap": "6", "ref": "US 127", "source:hgv:national_network": "Title 23: Highways Part 658 http://ecfr.gpoaccess.gov/cgi/t/text/text-idx?c=ecfr&rgn=div5&view=text&node=23:1.0.1.7.33&idno=23", "source:old_ref:fap": "ODOT http://www.dot.state.oh.us/Divisions/Planning/TechServ/prod_services/Pages/RI06.aspx http://www.dot.state.oh.us/Divisions/ContractAdmin/Contracts/Pages/NHS-FAP.aspx", "turn:lanes:both_ways": "left"}}, {"type": "way", "id": 559732714, "nodes": [197464796, 5398204228, 5398204229], "tags": {"change:backward": "no", "hgv": "designated", "hgv:national_network": "yes", "highway": "primary", "lanes": "3", "lanes:backward": "2", "lanes:forward": "1", "name": "Hamilton Avenue", "old_ref:fap": "6", "ref": "US 127", "source:hgv:national_network": "Title 23: Highways Part 658 http://ecfr.gpoaccess.gov/cgi/t/text/text-idx?c=ecfr&rgn=div5&view=text&node=23:1.0.1.7.33&idno=23", "source:old_ref:fap": "ODOT http://www.dot.state.oh.us/Divisions/Planning/TechServ/prod_services/Pages/RI06.aspx http://www.dot.state.oh.us/Divisions/ContractAdmin/Contracts/Pages/NHS-FAP.aspx", "turn:lanes:backward": "left|"}}, {"type": "way", "id": 559732719, "nodes": [5398204237, 197464796], "tags": {"change:forward": "no", "hgv": "designated", "hgv:national_network": "yes", "highway": "primary", "lanes": "3", "lanes:backward": "1", "lanes:forward": "2", "name": "Hamilton Avenue", "old_ref:fap": "6", "ref": "US 127", "source:hgv:national_network": "Title 23: Highways Part 658 http://ecfr.gpoaccess.gov/cgi/t/text/text-idx?c=ecfr&rgn=div5&view=text&node=23:1.0.1.7.33&idno=23", "source:old_ref:fap": "ODOT http://www.dot.state.oh.us/Divisions/Planning/TechServ/prod_services/Pages/RI06.aspx http://www.dot.state.oh.us/Divisions/ContractAdmin/Contracts/Pages/NHS-FAP.aspx", "turn:lanes:forward": "left|"}}, {"type": "way", "id": 559732723, "nodes": [197505123, 197505126, 2272266140, 197505130, 5398204231, 5398204238, 5398204237], "tags": {"hgv": "designated", "hgv:national_network": "yes", "highway": "primary", "lanes": "3", "lanes:backward": "1", "lanes:both_ways": "1", "lanes:forward": "1", "name": "Hamilton Avenue", "old_ref:fap": "6", "ref": "US 127", "source:hgv:national_network": "Title 23: Highways Part 658 http://ecfr.gpoaccess.gov/cgi/t/text/text-idx?c=ecfr&rgn=div5&view=text&node=23:1.0.1.7.33&idno=23", "source:old_ref:fap": "ODOT http://www.dot.state.oh.us/Divisions/Planning/TechServ/prod_services/Pages/RI06.aspx http://www.dot.state.oh.us/Divisions/ContractAdmin/Contracts/Pages/NHS-FAP.aspx", "turn:lanes:both_ways": "left"}}, {"type": "way", "id": 559732725, "nodes": [5398204255, 2099429045, 2099429044, 2099429366, 2099429118, 2099447180, 2099429304, 2099429140, 2099429051, 2099429142, 2099429434, 2099429016, 2099429473], "tags": {"highway": "unclassified"}}, {"type": "way", "id": 559732761, "nodes": [5398204352, 2099447125, 2099429438], "tags": {"change:forward": "no", "hgv": "designated", "hgv:national_network": "yes", "highway": "primary", "lanes": "3", "lanes:backward": "1", "lanes:forward": "2", "name": "Hamilton Avenue", "old_ref:fap": "6", "ref": "US 127", "source:hgv:national_network": "Title 23: Highways Part 658 http://ecfr.gpoaccess.gov/cgi/t/text/text-idx?c=ecfr&rgn=div5&view=text&node=23:1.0.1.7.33&idno=23", "source:old_ref:fap": "ODOT http://www.dot.state.oh.us/Divisions/Planning/TechServ/prod_services/Pages/RI06.aspx http://www.dot.state.oh.us/Divisions/ContractAdmin/Contracts/Pages/NHS-FAP.aspx", "tiger:cfcc": "A21", "tiger:county": "Hamilton, OH", "tiger:name_base": "Hamilton", "tiger:name_base_1": "United States Highway 127", "tiger:name_type": "Ave", "tiger:reviewed": "no", "tiger:zip_left": "45231", "tiger:zip_right": "45231", "turn:lanes:forward": "left|"}}, {"type": "way", "id": 559732762, "nodes": [2272264875, 10593935792, 5398204352], "tags": {"hgv": "designated", "hgv:national_network": "yes", "highway": "primary", "name": "Hamilton Avenue", "old_ref:fap": "6", "ref": "US 127", "source:hgv:national_network": "Title 23: Highways Part 658 http://ecfr.gpoaccess.gov/cgi/t/text/text-idx?c=ecfr&rgn=div5&view=text&node=23:1.0.1.7.33&idno=23", "source:old_ref:fap": "ODOT http://www.dot.state.oh.us/Divisions/Planning/TechServ/prod_services/Pages/RI06.aspx http://www.dot.state.oh.us/Divisions/ContractAdmin/Contracts/Pages/NHS-FAP.aspx", "tiger:cfcc": "A21", "tiger:county": "Hamilton, OH", "tiger:name_base": "Hamilton", "tiger:name_base_1": "United States Highway 127", "tiger:name_type": "Ave", "tiger:reviewed": "no", "tiger:zip_left": "45231", "tiger:zip_right": "45231"}}, {"type": "way", "id": 559732774, "nodes": [5398204379, 2523825214, 8002067516, 197505118, 5398204376, 5398204378, 8002067508, 5398204371, 2099429329, 2099429390, 5398204353, 8508883655, 8170232389, 8170232382, 9016096628, 9016096621, 2272266142, 2272264875], "tags": {"hgv": "designated", "hgv:national_network": "yes", "highway": "primary", "lanes": "3", "lanes:backward": "1", "lanes:both_ways": "1", "lanes:forward": "1", "name": "Hamilton Avenue", "old_ref:fap": "6", "ref": "US 127", "source:hgv:national_network": "Title 23: Highways Part 658 http://ecfr.gpoaccess.gov/cgi/t/text/text-idx?c=ecfr&rgn=div5&view=text&node=23:1.0.1.7.33&idno=23", "source:old_ref:fap": "ODOT http://www.dot.state.oh.us/Divisions/Planning/TechServ/prod_services/Pages/RI06.aspx http://www.dot.state.oh.us/Divisions/ContractAdmin/Contracts/Pages/NHS-FAP.aspx", "tiger:cfcc": "A21", "tiger:county": "Hamilton, OH", "tiger:name_base": "Hamilton", "tiger:name_base_1": "United States Highway 127", "tiger:name_type": "Ave", "tiger:reviewed": "no", "tiger:zip_left": "45231", "tiger:zip_right": "45231", "turn:lanes:both_ways": "left"}}, {"type": "way", "id": 559732775, "nodes": [5398204380, 9694808254, 5398204379], "tags": {"change:backward": "no", "hgv": "designated", "hgv:national_network": "yes", "highway": "primary", "lanes": "3", "lanes:backward": "2", "lanes:forward": "1", "name": "Hamilton Avenue", "old_ref:fap": "6", "ref": "US 127", "source:hgv:national_network": "Title 23: Highways Part 658 http://ecfr.gpoaccess.gov/cgi/t/text/text-idx?c=ecfr&rgn=div5&view=text&node=23:1.0.1.7.33&idno=23", "source:old_ref:fap": "ODOT http://www.dot.state.oh.us/Divisions/Planning/TechServ/prod_services/Pages/RI06.aspx http://www.dot.state.oh.us/Divisions/ContractAdmin/Contracts/Pages/NHS-FAP.aspx", "tiger:cfcc": "A21", "tiger:county": "Hamilton, OH", "tiger:name_base": "Hamilton", "tiger:name_base_1": "United States Highway 127", "tiger:name_type": "Ave", "tiger:reviewed": "no", "tiger:zip_left": "45231", "tiger:zip_right": "45231", "turn:lanes:backward": "left|"}}, {"type": "way", "id": 559732779, "nodes": [1070468597, 2489440244, 197448738], "tags": {"highway": "residential", "name": "Adams Road", "oneway": "no", "tiger:cfcc": "A41", "tiger:county": "Hamilton, OH", "tiger:name_base": "Adams", "tiger:name_type": "Rd", "tiger:reviewed": "no", "tiger:zip_left": "45231", "tiger:zip_right": "45231"}}, {"type": "way", "id": 559732780, "nodes": [197505116, 2489440249, 197448736], "tags": {"change:forward": "no", "hgv": "designated", "hgv:national_network": "yes", "highway": "primary", "lanes": "4", "lanes:backward": "1", "lanes:forward": "3", "name": "Hamilton Avenue", "old_ref:fap": "6", "ref": "US 127", "source:hgv:national_network": "Title 23: Highways Part 658 http://ecfr.gpoaccess.gov/cgi/t/text/text-idx?c=ecfr&rgn=div5&view=text&node=23:1.0.1.7.33&idno=23", "source:old_ref:fap": "ODOT http://www.dot.state.oh.us/Divisions/Planning/TechServ/prod_services/Pages/RI06.aspx http://www.dot.state.oh.us/Divisions/ContractAdmin/Contracts/Pages/NHS-FAP.aspx", "tiger:cfcc": "A21", "tiger:county": "Hamilton, OH", "tiger:name_base": "Hamilton", "tiger:name_base_1": "United States Highway 127", "tiger:name_type": "Ave", "tiger:reviewed": "no", "tiger:zip_left": "45231", "tiger:zip_right": "45231", "turn:lanes:forward": "left|through|right"}}, {"type": "way", "id": 559732782, "nodes": [5398204385, 5398204387, 5398204392, 197505116], "tags": {"hgv": "designated", "hgv:national_network": "yes", "highway": "primary", "lanes": "3", "lanes:backward": "1", "lanes:both_ways": "1", "lanes:forward": "1", "name": "Hamilton Avenue", "old_ref:fap": "6", "ref": "US 127", "source:hgv:national_network": "Title 23: Highways Part 658 http://ecfr.gpoaccess.gov/cgi/t/text/text-idx?c=ecfr&rgn=div5&view=text&node=23:1.0.1.7.33&idno=23", "source:old_ref:fap": "ODOT http://www.dot.state.oh.us/Divisions/Planning/TechServ/prod_services/Pages/RI06.aspx http://www.dot.state.oh.us/Divisions/ContractAdmin/Contracts/Pages/NHS-FAP.aspx", "tiger:cfcc": "A21", "tiger:county": "Hamilton, OH", "tiger:name_base": "Hamilton", "tiger:name_base_1": "United States Highway 127", "tiger:name_type": "Ave", "tiger:reviewed": "no", "tiger:zip_left": "45231", "tiger:zip_right": "45231", "turn:lanes:both_ways": "left"}}, {"type": "way", "id": 559732783, "nodes": [197505113, 5398204388, 5398204385], "tags": {"change:backward": "no", "hgv": "designated", "hgv:national_network": "yes", "highway": "primary", "lanes": "3", "lanes:backward": "2", "lanes:forward": "1", "name": "Hamilton Avenue", "old_ref:fap": "6", "ref": "US 127", "source:hgv:national_network": "Title 23: Highways Part 658 http://ecfr.gpoaccess.gov/cgi/t/text/text-idx?c=ecfr&rgn=div5&view=text&node=23:1.0.1.7.33&idno=23", "source:old_ref:fap": "ODOT http://www.dot.state.oh.us/Divisions/Planning/TechServ/prod_services/Pages/RI06.aspx http://www.dot.state.oh.us/Divisions/ContractAdmin/Contracts/Pages/NHS-FAP.aspx", "tiger:cfcc": "A21", "tiger:county": "Hamilton, OH", "tiger:name_base": "Hamilton", "tiger:name_base_1": "United States Highway 127", "tiger:name_type": "Ave", "tiger:reviewed": "no", "tiger:zip_left": "45231", "tiger:zip_right": "45231", "turn:lanes:backward": "left|"}}, {"type": "way", "id": 559732797, "nodes": [5398204430, 5398204431, 5398204415, 197505110, 2489440221, 197505113], "tags": {"hgv": "designated", "hgv:national_network": "yes", "highway": "primary", "lanes": "3", "lanes:backward": "1", "lanes:both_ways": "1", "lanes:forward": "1", "name": "Hamilton Avenue", "old_ref:fap": "6", "ref": "US 127", "source:hgv:national_network": "Title 23: Highways Part 658 http://ecfr.gpoaccess.gov/cgi/t/text/text-idx?c=ecfr&rgn=div5&view=text&node=23:1.0.1.7.33&idno=23", "source:old_ref:fap": "ODOT http://www.dot.state.oh.us/Divisions/Planning/TechServ/prod_services/Pages/RI06.aspx http://www.dot.state.oh.us/Divisions/ContractAdmin/Contracts/Pages/NHS-FAP.aspx", "tiger:cfcc": "A21", "tiger:county": "Hamilton, OH", "tiger:name_base": "Hamilton", "tiger:name_base_1": "United States Highway 127", "tiger:name_type": "Ave", "tiger:reviewed": "no", "tiger:zip_left": "45231", "tiger:zip_right": "45231", "turn:lanes:both_ways": "left"}}, {"type": "way", "id": 559732798, "nodes": [197418748, 2489440228, 5398204430], "tags": {"change:backward": "no", "hgv": "designated", "hgv:national_network": "yes", "highway": "primary", "lanes": "3", "lanes:backward": "2", "lanes:forward": "1", "name": "Hamilton Avenue", "old_ref:fap": "6", "ref": "US 127", "source:hgv:national_network": "Title 23: Highways Part 658 http://ecfr.gpoaccess.gov/cgi/t/text/text-idx?c=ecfr&rgn=div5&view=text&node=23:1.0.1.7.33&idno=23", "source:old_ref:fap": "ODOT http://www.dot.state.oh.us/Divisions/Planning/TechServ/prod_services/Pages/RI06.aspx http://www.dot.state.oh.us/Divisions/ContractAdmin/Contracts/Pages/NHS-FAP.aspx", "tiger:cfcc": "A21", "tiger:county": "Hamilton, OH", "tiger:name_base": "Hamilton", "tiger:name_base_1": "United States Highway 127", "tiger:name_type": "Ave", "tiger:reviewed": "no", "tiger:zip_left": "45231", "tiger:zip_right": "45231", "turn:lanes:backward": "left|"}}, {"type": "way", "id": 559732815, "nodes": [5398204518, 8671457196, 8671457211, 8671517325, 197479101, 2489447212, 8000472804, 2090685468, 2489447247, 197452781, 2489447264, 5398204508, 2489447214, 197505109], "tags": {"hgv": "designated", "hgv:national_network": "yes", "highway": "primary", "lanes": "2", "name": "Hamilton Avenue", "old_ref:fap": "6", "ref": "US 127", "source:hgv:national_network": "Title 23: Highways Part 658 http://ecfr.gpoaccess.gov/cgi/t/text/text-idx?c=ecfr&rgn=div5&view=text&node=23:1.0.1.7.33&idno=23", "source:old_ref:fap": "ODOT http://www.dot.state.oh.us/Divisions/Planning/TechServ/prod_services/Pages/RI06.aspx http://www.dot.state.oh.us/Divisions/ContractAdmin/Contracts/Pages/NHS-FAP.aspx", "tiger:cfcc": "A21", "tiger:county": "Hamilton, OH", "tiger:name_base": "Hamilton", "tiger:name_base_1": "United States Highway 127", "tiger:name_type": "Ave", "tiger:reviewed": "no", "tiger:zip_left": "45231", "tiger:zip_right": "45231"}}, {"type": "way", "id": 559732816, "nodes": [5398204520, 2489447245, 197505106], "tags": {"change:backward": "no", "hgv": "designated", "hgv:national_network": "yes", "highway": "primary", "lanes": "4", "name": "Hamilton Avenue", "old_ref:fap": "6", "ref": "US 127", "source:hgv:national_network": "Title 23: Highways Part 658 http://ecfr.gpoaccess.gov/cgi/t/text/text-idx?c=ecfr&rgn=div5&view=text&node=23:1.0.1.7.33&idno=23", "source:old_ref:fap": "ODOT http://www.dot.state.oh.us/Divisions/Planning/TechServ/prod_services/Pages/RI06.aspx http://www.dot.state.oh.us/Divisions/ContractAdmin/Contracts/Pages/NHS-FAP.aspx", "tiger:cfcc": "A21", "tiger:county": "Hamilton, OH", "tiger:name_base": "Hamilton", "tiger:name_base_1": "United States Highway 127", "tiger:name_type": "Ave", "tiger:reviewed": "no", "tiger:zip_left": "45231", "tiger:zip_right": "45231"}}, {"type": "way", "id": 559732817, "nodes": [197505106, 2489447225, 5398204518], "tags": {"hgv": "designated", "hgv:national_network": "yes", "highway": "primary", "lanes": "3", "lanes:backward": "2", "lanes:forward": "1", "name": "Hamilton Avenue", "old_ref:fap": "6", "ref": "US 127", "source:hgv:national_network": "Title 23: Highways Part 658 http://ecfr.gpoaccess.gov/cgi/t/text/text-idx?c=ecfr&rgn=div5&view=text&node=23:1.0.1.7.33&idno=23", "source:old_ref:fap": "ODOT http://www.dot.state.oh.us/Divisions/Planning/TechServ/prod_services/Pages/RI06.aspx http://www.dot.state.oh.us/Divisions/ContractAdmin/Contracts/Pages/NHS-FAP.aspx", "tiger:cfcc": "A21", "tiger:county": "Hamilton, OH", "tiger:name_base": "Hamilton", "tiger:name_base_1": "United States Highway 127", "tiger:name_type": "Ave", "tiger:reviewed": "no", "tiger:zip_left": "45231", "tiger:zip_right": "45231"}}, {"type": "way", "id": 559732819, "nodes": [197505104, 7147693032, 5398204520], "tags": {"change:lanes:backward": "no|not_left|yes", "hgv": "designated", "hgv:national_network": "yes", "highway": "primary", "lanes": "5", "lanes:backward": "3", "lanes:forward": "2", "name": "Hamilton Avenue", "old_ref:fap": "6", "ref": "US 127", "source:hgv:national_network": "Title 23: Highways Part 658 http://ecfr.gpoaccess.gov/cgi/t/text/text-idx?c=ecfr&rgn=div5&view=text&node=23:1.0.1.7.33&idno=23", "source:old_ref:fap": "ODOT http://www.dot.state.oh.us/Divisions/Planning/TechServ/prod_services/Pages/RI06.aspx http://www.dot.state.oh.us/Divisions/ContractAdmin/Contracts/Pages/NHS-FAP.aspx", "tiger:cfcc": "A21", "tiger:county": "Hamilton, OH", "tiger:name_base": "Hamilton", "tiger:name_base_1": "United States Highway 127", "tiger:name_type": "Ave", "tiger:reviewed": "no", "tiger:zip_left": "45231", "tiger:zip_right": "45231", "turn:lanes:backward": "left||"}}, {"type": "way", "id": 560119787, "nodes": [197510442, 197452746], "tags": {"highway": "residential", "name": "Mallory Lane", "tiger:cfcc": "A41", "tiger:county": "Hamilton, OH", "tiger:name_base": "Mallory", "tiger:name_type": "Ln", "tiger:reviewed": "no", "tiger:zip_left": "45231", "tiger:zip_right": "45231"}}, {"type": "way", "id": 560119798, "nodes": [5401549595, 1070468960], "tags": {"change:forward": "no", "highway": "residential", "lanes": "3", "lanes:backward": "1", "lanes:forward": "2", "name": "Adams Road", "tiger:cfcc": "A41", "tiger:county": "Hamilton, OH", "tiger:name_base": "Adams", "tiger:name_type": "Rd", "tiger:reviewed": "no", "tiger:zip_left": "45231", "tiger:zip_right": "45231", "turn:lanes:forward": "left|"}}, {"type": "way", "id": 560119799, "nodes": [1070468960, 2916078930, 8670911659, 7127897484, 197448742, 8169690476, 6968675612, 6971316536, 7128004957, 2099447117, 197448744, 2099447211, 197448746, 2099447177, 197448748], "tags": {"highway": "residential", "name": "Adams Road", "tiger:cfcc": "A41", "tiger:county": "Hamilton, OH", "tiger:name_base": "Adams", "tiger:name_type": "Rd", "tiger:reviewed": "no", "tiger:zip_left": "45231", "tiger:zip_right": "45231"}}, {"type": "way", "id": 653860513, "nodes": [1070468157, 197416141, 1070468506, 2489440254, 197418748, 2489440255, 1070467951, 2489440253, 197418749, 2489440233, 1070468927, 197418751], "tags": {"highway": "residential", "name": "Hill Avenue", "tiger:cfcc": "A41", "tiger:county": "Hamilton, OH", "tiger:name_base": "Hill", "tiger:name_type": "Ave", "tiger:reviewed": "no", "tiger:zip_left": "45231", "tiger:zip_right": "45231"}}, {"type": "way", "id": 862875849, "nodes": [197436127, 8038454369, 8038454361, 8038454376, 8038454368, 8038454362, 8038454360, 8038454374, 8038454366, 8038454354, 8038454358, 8038454372, 8038454364, 8038454356, 8038454370, 8038454371, 8038454363, 8038454355, 197436127], "tags": {"bicycle": "yes", "foot": "yes", "highway": "residential", "lane_markings": "no", "lanes": "1", "name": "Roettele Place", "oneway": "yes", "surface": "concrete", "tiger:cfcc": "A41", "tiger:county": "Hamilton, OH", "tiger:name_base": "Roettele", "tiger:name_type": "Pl", "tiger:reviewed": "no", "tiger:zip_left": "45231", "tiger:zip_right": "45231"}}, {"type": "way", "id": 862875850, "nodes": [197436127, 197436128, 197436129], "tags": {"bicycle": "yes", "foot": "yes", "highway": "residential", "lane_markings": "no", "lanes": "2", "name": "Roettele Place", "oneway": "no", "surface": "concrete", "tiger:cfcc": "A41", "tiger:county": "Hamilton, OH", "tiger:name_base": "Roettele", "tiger:name_type": "Pl", "tiger:reviewed": "no", "tiger:zip_left": "45231", "tiger:zip_right": "45231"}}, {"type": "way", "id": 1043380813, "nodes": [373776639, 373771620, 373771621, 373771622], "tags": {"destination:lanes": "none|none;Hamilton Avenue;Mount Healthy;North College Hill", "hgv": "designated", "hgv:national_network": "yes", "highway": "motorway", "lanes": "2", "maxspeed": "65 mph", "name": "Ronald Reagan Cross County Highway", "old_ref": "RR", "old_ref:fap": "2", "oneway": "yes", "ref": "SR 126", "source:hgv:national_network": "Title 23: Highways Part 658 http://ecfr.gpoaccess.gov/cgi/t/text/text-idx?c=ecfr&rgn=div5&view=text&node=23:1.0.1.7.33&idno=23", "source:old_ref:fap": "ODOT http://www.dot.state.oh.us/Divisions/Planning/TechServ/prod_services/Pages/RI06.aspx http://www.dot.state.oh.us/Divisions/ContractAdmin/Contracts/Pages/NHS-FAP.aspx", "tiger:cfcc": "A31", "tiger:county": "Hamilton, OH", "tiger:name_base": "Ronald Reagan Cross County Hwy", "tiger:name_base_1": "State Route 126", "tiger:reviewed": "no", "tiger:zip_left": "45231", "tiger:zip_right": "45231", "turn:lanes": "none|through;slight_right"}}]}